tarefa1_extra/extra.vhd
library ieee;
use ieee.std_logic_1164.all;

-- Multiplexador 3 para 1 de dois bits pedido na Atividade Extra.
entity mux3_2bit is
    port (
        S       : in  std_logic_vector(1 downto 0);
        U, V, W : in  std_logic_vector(1 downto 0);
        M       : out std_logic_vector(1 downto 0)
    );
end mux3_2bit;

architecture behavioral of mux3_2bit is
begin
    process (S, U, V, W)
    begin
        case S is
            when "00"   => M <= U;
            when "01"   => M <= V;
            when "10"   => M <= W;
            when others => M <= U;
        end case;
    end process;
end behavioral;

library ieee;
use ieee.std_logic_1164.all;

-- Mesmo decodificador da Parte 4, para os displays ativos em nivel baixo.
entity char_7seg is
    port (
        C       : in  std_logic_vector(1 downto 0);
        DISPLAY : out std_logic_vector(0 to 6)
    );
end char_7seg;

architecture rtl of char_7seg is
    constant CHAR_D     : std_logic_vector(0 to 6) := "1000010";
    constant CHAR_E     : std_logic_vector(0 to 6) := "0110000";
    constant CHAR_0     : std_logic_vector(0 to 6) := "0000001";
    constant CHAR_BLANK : std_logic_vector(0 to 6) := "1111111";
begin
    with C select
        DISPLAY <= CHAR_D     when "00",
                   CHAR_E     when "01",
                   CHAR_0     when "10",
                   CHAR_BLANK when others;
end rtl;

library ieee;
use ieee.std_logic_1164.all;

entity extra is
    port (
        SW               : in  std_logic_vector(9 downto 0);
        LEDG             : out std_logic_vector(9 downto 0);
        HEX2, HEX1, HEX0 : out std_logic_vector(0 to 6)
    );
end extra;

architecture structural of extra is
    signal SELECTOR                   : std_logic_vector(1 downto 0);
    signal CH0, CH1, CH2              : std_logic_vector(1 downto 0);
    signal H2_CHAR, H1_CHAR, H0_CHAR : std_logic_vector(1 downto 0);
begin
    LEDG <= SW;

    SELECTOR <= SW(9 downto 8);
    CH0 <= SW(5 downto 4);
    CH1 <= SW(3 downto 2);
    CH2 <= SW(1 downto 0);
	 
    MUX_HEX2 : entity work.mux3_2bit(behavioral)
        port map (SELECTOR, CH0, CH1, CH2, H2_CHAR);

    MUX_HEX1 : entity work.mux3_2bit(behavioral)
        port map (SELECTOR, CH1, CH2, CH0, H1_CHAR);

    MUX_HEX0 : entity work.mux3_2bit(behavioral)
        port map (SELECTOR, CH2, CH0, CH1, H0_CHAR);

    DEC_HEX2 : entity work.char_7seg(rtl) port map (H2_CHAR, HEX2);
    DEC_HEX1 : entity work.char_7seg(rtl) port map (H1_CHAR, HEX1);
    DEC_HEX0 : entity work.char_7seg(rtl) port map (H0_CHAR, HEX0);
end structural;

tarefa1_extra/extra_tb.vhd
library ieee;
use ieee.std_logic_1164.all;
use ieee.numeric_std.all;

entity extra_tb is
end extra_tb;

architecture test of extra_tb is
    signal SW               : std_logic_vector(9 downto 0) := (others => '0');
    signal LEDG             : std_logic_vector(9 downto 0);
    signal HEX2, HEX1, HEX0 : std_logic_vector(0 to 6);

    type code_array is array (0 to 2) of std_logic_vector(1 downto 0);

    function decode(C : std_logic_vector(1 downto 0))
        return std_logic_vector is
    begin
        case C is
            when "00"   => return "1000010"; -- d
            when "01"   => return "0110000"; -- E
            when "10"   => return "0000001"; -- 0
            when others => return "1111111"; -- apagado
        end case;
    end function;
begin
    DUT : entity work.extra(structural)
        port map (SW, LEDG, HEX2, HEX1, HEX0);

    stimulus : process
        variable sw_value : std_logic_vector(9 downto 0);
        variable chars    : code_array;
        variable rotation : integer;
    begin
        for value in 0 to 1023 loop
            sw_value := std_logic_vector(to_unsigned(value, SW'length));
            SW <= sw_value;
            wait for 1 ns;

            chars(0) := sw_value(5 downto 4);
            chars(1) := sw_value(3 downto 2);
            chars(2) := sw_value(1 downto 0);
            rotation := to_integer(unsigned(sw_value(9 downto 8)));
            if rotation = 3 then
                rotation := 0;
            end if;

            assert LEDG = sw_value
                report "LEDG nao acompanha SW" severity failure;
            assert HEX2 = decode(chars((rotation + 0) mod 3))
                report "Rotacao incorreta em HEX2" severity failure;
            assert HEX1 = decode(chars((rotation + 1) mod 3))
                report "Rotacao incorreta em HEX1" severity failure;
            assert HEX0 = decode(chars((rotation + 2) mod 3))
                report "Rotacao incorreta em HEX0" severity failure;
        end loop;

        report "Atividade Extra: todas as 1024 combinacoes aprovadas"
            severity note;
        wait;
    end process;
end test;

tarefa1_extra/extra.vcd
$date
	Wed Sep 16 17:39:04 2026
$end
$version
	ModelSim Version 10.1d
$end
$timescale
	1ps
$end
$scope module extra_tb $end
$var wire 1 ! SW [9] $end
$var wire 1 " SW [8] $end
$var wire 1 # SW [7] $end
$var wire 1 $ SW [6] $end
$var wire 1 % SW [5] $end
$var wire 1 & SW [4] $end
$var wire 1 ' SW [3] $end
$var wire 1 ( SW [2] $end
$var wire 1 ) SW [1] $end
$var wire 1 * SW [0] $end
$var wire 1 + LEDG [9] $end
$var wire 1 , LEDG [8] $end
$var wire 1 - LEDG [7] $end
$var wire 1 . LEDG [6] $end
$var wire 1 / LEDG [5] $end
$var wire 1 0 LEDG [4] $end
$var wire 1 1 LEDG [3] $end
$var wire 1 2 LEDG [2] $end
$var wire 1 3 LEDG [1] $end
$var wire 1 4 LEDG [0] $end
$var wire 1 5 HEX2 [0] $end
$var wire 1 6 HEX2 [1] $end
$var wire 1 7 HEX2 [2] $end
$var wire 1 8 HEX2 [3] $end
$var wire 1 9 HEX2 [4] $end
$var wire 1 : HEX2 [5] $end
$var wire 1 ; HEX2 [6] $end
$var wire 1 < HEX1 [0] $end
$var wire 1 = HEX1 [1] $end
$var wire 1 > HEX1 [2] $end
$var wire 1 ? HEX1 [3] $end
$var wire 1 @ HEX1 [4] $end
$var wire 1 A HEX1 [5] $end
$var wire 1 B HEX1 [6] $end
$var wire 1 C HEX0 [0] $end
$var wire 1 D HEX0 [1] $end
$var wire 1 E HEX0 [2] $end
$var wire 1 F HEX0 [3] $end
$var wire 1 G HEX0 [4] $end
$var wire 1 H HEX0 [5] $end
$var wire 1 I HEX0 [6] $end
$scope module DUT $end
$var wire 1 ! SW [9] $end
$var wire 1 " SW [8] $end
$var wire 1 # SW [7] $end
$var wire 1 $ SW [6] $end
$var wire 1 % SW [5] $end
$var wire 1 & SW [4] $end
$var wire 1 ' SW [3] $end
$var wire 1 ( SW [2] $end
$var wire 1 ) SW [1] $end
$var wire 1 * SW [0] $end
$var wire 1 + LEDG [9] $end
$var wire 1 , LEDG [8] $end
$var wire 1 - LEDG [7] $end
$var wire 1 . LEDG [6] $end
$var wire 1 / LEDG [5] $end
$var wire 1 0 LEDG [4] $end
$var wire 1 1 LEDG [3] $end
$var wire 1 2 LEDG [2] $end
$var wire 1 3 LEDG [1] $end
$var wire 1 4 LEDG [0] $end
$var wire 1 5 HEX2 [0] $end
$var wire 1 6 HEX2 [1] $end
$var wire 1 7 HEX2 [2] $end
$var wire 1 8 HEX2 [3] $end
$var wire 1 9 HEX2 [4] $end
$var wire 1 : HEX2 [5] $end
$var wire 1 ; HEX2 [6] $end
$var wire 1 < HEX1 [0] $end
$var wire 1 = HEX1 [1] $end
$var wire 1 > HEX1 [2] $end
$var wire 1 ? HEX1 [3] $end
$var wire 1 @ HEX1 [4] $end
$var wire 1 A HEX1 [5] $end
$var wire 1 B HEX1 [6] $end
$var wire 1 C HEX0 [0] $end
$var wire 1 D HEX0 [1] $end
$var wire 1 E HEX0 [2] $end
$var wire 1 F HEX0 [3] $end
$var wire 1 G HEX0 [4] $end
$var wire 1 H HEX0 [5] $end
$var wire 1 I HEX0 [6] $end
$var wire 1 J SELECTOR [1] $end
$var wire 1 K SELECTOR [0] $end
$var wire 1 L CH0 [1] $end
$var wire 1 M CH0 [0] $end
$var wire 1 N CH1 [1] $end
$var wire 1 O CH1 [0] $end
$var wire 1 P CH2 [1] $end
$var wire 1 Q CH2 [0] $end
$var wire 1 R H2_CHAR [1] $end
$var wire 1 S H2_CHAR [0] $end
$var wire 1 T H1_CHAR [1] $end
$var wire 1 U H1_CHAR [0] $end
$var wire 1 V H0_CHAR [1] $end
$var wire 1 W H0_CHAR [0] $end
$scope module MUX_HEX2 $end
$var wire 1 J S [1] $end
$var wire 1 K S [0] $end
$var wire 1 L U [1] $end
$var wire 1 M U [0] $end
$var wire 1 N V [1] $end
$var wire 1 O V [0] $end
$var wire 1 P W [1] $end
$var wire 1 Q W [0] $end
$var wire 1 R M [1] $end
$var wire 1 S M [0] $end
$upscope $end
$scope module MUX_HEX1 $end
$var wire 1 J S [1] $end
$var wire 1 K S [0] $end
$var wire 1 N U [1] $end
$var wire 1 O U [0] $end
$var wire 1 P V [1] $end
$var wire 1 Q V [0] $end
$var wire 1 L W [1] $end
$var wire 1 M W [0] $end
$var wire 1 T M [1] $end
$var wire 1 U M [0] $end
$upscope $end
$scope module MUX_HEX0 $end
$var wire 1 J S [1] $end
$var wire 1 K S [0] $end
$var wire 1 P U [1] $end
$var wire 1 Q U [0] $end
$var wire 1 L V [1] $end
$var wire 1 M V [0] $end
$var wire 1 N W [1] $end
$var wire 1 O W [0] $end
$var wire 1 V M [1] $end
$var wire 1 W M [0] $end
$upscope $end
$scope module DEC_HEX2 $end
$var wire 1 R C [1] $end
$var wire 1 S C [0] $end
$var wire 1 5 DISPLAY [0] $end
$var wire 1 6 DISPLAY [1] $end
$var wire 1 7 DISPLAY [2] $end
$var wire 1 8 DISPLAY [3] $end
$var wire 1 9 DISPLAY [4] $end
$var wire 1 : DISPLAY [5] $end
$var wire 1 ; DISPLAY [6] $end
$upscope $end
$scope module DEC_HEX1 $end
$var wire 1 T C [1] $end
$var wire 1 U C [0] $end
$var wire 1 < DISPLAY [0] $end
$var wire 1 = DISPLAY [1] $end
$var wire 1 > DISPLAY [2] $end
$var wire 1 ? DISPLAY [3] $end
$var wire 1 @ DISPLAY [4] $end
$var wire 1 A DISPLAY [5] $end
$var wire 1 B DISPLAY [6] $end
$upscope $end
$scope module DEC_HEX0 $end
$var wire 1 V C [1] $end
$var wire 1 W C [0] $end
$var wire 1 C DISPLAY [0] $end
$var wire 1 D DISPLAY [1] $end
$var wire 1 E DISPLAY [2] $end
$var wire 1 F DISPLAY [3] $end
$var wire 1 G DISPLAY [4] $end
$var wire 1 H DISPLAY [5] $end
$var wire 1 I DISPLAY [6] $end
$upscope $end
$upscope $end
$upscope $end
$enddefinitions $end
#0
$dumpvars
0!
0"
0#
0$
0%
0&
0'
0(
0)
0*
0+
0,
0-
0.
0/
00
01
02
03
04
15
06
07
08
09
1:
0;
1<
0=
0>
0?
0@
1A
0B
1C
0D
0E
0F
0G
1H
0I
0J
0K
0L
0M
0N
0O
0P
0Q
0R
0S
0T
0U
0V
0W
$end
#1000
1*
14
1Q
1W
0H
1E
1D
0C
#2000
0*
1)
04
13
0Q
1P
0W
1V
1I
0E
0D
#3000
1*
14
1Q
1W
1H
1G
1F
1E
1D
1C
#4000
0*
0)
1(
04
03
12
0Q
0P
1O
1U
0W
0V
0A
1>
1=
0<
0I
0G
0F
0E
0D
#5000
1*
14
1Q
1W
0H
1E
1D
0C
#6000
0*
1)
04
13
0Q
1P
0W
1V
1I
0E
0D
#7000
1*
14
1Q
1W
1H
1G
1F
1E
1D
1C
#8000
0*
0)
0(
1'
04
03
02
11
0Q
0P
0O
1N
0U
1T
0W
0V
1B
0>
0=
0I
0G
0F
0E
0D
#9000
1*
14
1Q
1W
0H
1E
1D
0C
#10000
0*
1)
04
13
0Q
1P
0W
1V
1I
0E
0D
#11000
1*
14
1Q
1W
1H
1G
1F
1E
1D
1C
#12000
0*
0)
1(
04
03
12
0Q
0P
1O
1U
0W
0V
1A
1@
1?
1>
1=
1<
0I
0G
0F
0E
0D
#13000
1*
14
1Q
1W
0H
1E
1D
0C
#14000
0*
1)
04
13
0Q
1P
0W
1V
1I
0E
0D
#15000
1*
14
1Q
1W
1H
1G
1F
1E
1D
1C
#16000
0*
0)
0(
0'
1&
04
03
02
01
10
0Q
0P
0O
0N
1M
1S
0U
0T
0W
0V
0:
17
16
05
0B
0@
0?
0>
0=
0I
0G
0F
0E
0D
#17000
1*
14
1Q
1W
0H
1E
1D
0C
#18000
0*
1)
04
13
0Q
1P
0W
1V
1I
0E
0D
#19000
1*
14
1Q
1W
1H
1G
1F
1E
1D
1C
#20000
0*
0)
1(
04
03
12
0Q
0P
1O
1U
0W
0V
0A
1>
1=
0<
0I
0G
0F
0E
0D
#21000
1*
14
1Q
1W
0H
1E
1D
0C
#22000
0*
1)
04
13
0Q
1P
0W
1V
1I
0E
0D
#23000
1*
14
1Q
1W
1H
1G
1F
1E
1D
1C
#24000
0*
0)
0(
1'
04
03
02
11
0Q
0P
0O
1N
0U
1T
0W
0V
1B
0>
0=
0I
0G
0F
0E
0D
#25000
1*
14
1Q
1W
0H
1E
1D
0C
#26000
0*
1)
04
13
0Q
1P
0W
1V
1I
0E
0D
#27000
1*
14
1Q
1W
1H
1G
1F
1E
1D
1C
#28000
0*
0)
1(
04
03
12
0Q
0P
1O
1U
0W
0V
1A
1@
1?
1>
1=
1<
0I
0G
0F
0E
0D
#29000
1*
14
1Q
1W
0H
1E
1D
0C
#30000
0*
1)
04
13
0Q
1P
0W
1V
1I
0E
0D
#31000
1*
14
1Q
1W
1H
1G
1F
1E
1D
1C
#32000
0*
0)
0(
0'
0&
1%
04
03
02
01
00
1/
0Q
0P
0O
0N
0M
1L
0S
1R
0U
0T
0W
0V
1;
07
06
0B
0@
0?
0>
0=
0I
0G
0F
0E
0D
#33000
1*
14
1Q
1W
0H
1E
1D
0C
#34000
0*
1)
04
13
0Q
1P
0W
1V
1I
0E
0D
#35000
1*
14
1Q
1W
1H
1G
1F
1E
1D
1C
#36000
0*
0)
1(
04
03
12
0Q
0P
1O
1U
0W
0V
0A
1>
1=
0<
0I
0G
0F
0E
0D
#37000
1*
14
1Q
1W
0H
1E
1D
0C
#38000
0*
1)
04
13
0Q
1P
0W
1V
1I
0E
0D
#39000
1*
14
1Q
1W
1H
1G
1F
1E
1D
1C
#40000
0*
0)
0(
1'
04
03
02
11
0Q
0P
0O
1N
0U
1T
0W
0V
1B
0>
0=
0I
0G
0F
0E
0D
#41000
1*
14
1Q
1W
0H
1E
1D
0C
#42000
0*
1)
04
13
0Q
1P
0W
1V
1I
0E
0D
#43000
1*
14
1Q
1W
1H
1G
1F
1E
1D
1C
#44000
0*
0)
1(
04
03
12
0Q
0P
1O
1U
0W
0V
1A
1@
1?
1>
1=
1<
0I
0G
0F
0E
0D
#45000
1*
14
1Q
1W
0H
1E
1D
0C
#46000
0*
1)
04
13
0Q
1P
0W
1V
1I
0E
0D
#47000
1*
14
1Q
1W
1H
1G
1F
1E
1D
1C
#48000
0*
0)
0(
0'
1&
04
03
02
01
10
0Q
0P
0O
0N
1M
1S
0U
0T
0W
0V
1:
19
18
17
16
15
0B
0@
0?
0>
0=
0I
0G
0F
0E
0D
#49000
1*
14
1Q
1W
0H
1E
1D
0C
#50000
0*
1)
04
13
0Q
1P
0W
1V
1I
0E
0D
#51000
1*
14
1Q
1W
1H
1G
1F
1E
1D
1C
#52000
0*
0)
1(
04
03
12
0Q
0P
1O
1U
0W
0V
0A
1>
1=
0<
0I
0G
0F
0E
0D
#53000
1*
14
1Q
1W
0H
1E
1D
0C
#54000
0*
1)
04
13
0Q
1P
0W
1V
1I
0E
0D
#55000
1*
14
1Q
1W
1H
1G
1F
1E
1D
1C
#56000
0*
0)
0(
1'
04
03
02
11
0Q
0P
0O
1N
0U
1T
0W
0V
1B
0>
0=
0I
0G
0F
0E
0D
#57000
1*
14
1Q
1W
0H
1E
1D
0C
#58000
0*
1)
04
13
0Q
1P
0W
1V
1I
0E
0D
#59000
1*
14
1Q
1W
1H
1G
1F
1E
1D
1C
#60000
0*
0)
1(
04
03
12
0Q
0P
1O
1U
0W
0V
1A
1@
1?
1>
1=
1<
0I
0G
0F
0E
0D
#61000
1*
14
1Q
1W
0H
1E
1D
0C
#62000
0*
1)
04
13
0Q
1P
0W
1V
1I
0E
0D
#63000
1*
14
1Q
1W
1H
1G
1F
1E
1D
1C
#64000
0*
0)
0(
0'
0&
0%
1$
04
03
02
01
00
0/
1.
0Q
0P
0O
0N
0M
0L
0S
0R
0U
0T
0W
0V
0;
09
08
07
06
0B
0@
0?
0>
0=
0I
0G
0F
0E
0D
#65000
1*
14
1Q
1W
0H
1E
1D
0C
#66000
0*
1)
04
13
0Q
1P
0W
1V
1I
0E
0D
#67000
1*
14
1Q
1W
1H
1G
1F
1E
1D
1C
#68000
0*
0)
1(
04
03
12
0Q
0P
1O
1U
0W
0V
0A
1>
1=
0<
0I
0G
0F
0E
0D
#69000
1*
14
1Q
1W
0H
1E
1D
0C
#70000
0*
1)
04
13
0Q
1P
0W
1V
1I
0E
0D
#71000
1*
14
1Q
1W
1H
1G
1F
1E
1D
1C
#72000
0*
0)
0(
1'
04
03
02
11
0Q
0P
0O
1N
0U
1T
0W
0V
1B
0>
0=
0I
0G
0F
0E
0D
#73000
1*
14
1Q
1W
0H
1E
1D
0C
#74000
0*
1)
04
13
0Q
1P
0W
1V
1I
0E
0D
#75000
1*
14
1Q
1W
1H
1G
1F
1E
1D
1C
#76000
0*
0)
1(
04
03
12
0Q
0P
1O
1U
0W
0V
1A
1@
1?
1>
1=
1<
0I
0G
0F
0E
0D
#77000
1*
14
1Q
1W
0H
1E
1D
0C
#78000
0*
1)
04
13
0Q
1P
0W
1V
1I
0E
0D
#79000
1*
14
1Q
1W
1H
1G
1F
1E
1D
1C
#80000
0*
0)
0(
0'
1&
04
03
02
01
10
0Q
0P
0O
0N
1M
1S
0U
0T
0W
0V
0:
17
16
05
0B
0@
0?
0>
0=
0I
0G
0F
0E
0D
#81000
1*
14
1Q
1W
0H
1E
1D
0C
#82000
0*
1)
04
13
0Q
1P
0W
1V
1I
0E
0D
#83000
1*
14
1Q
1W
1H
1G
1F
1E
1D
1C
#84000
0*
0)
1(
04
03
12
0Q
0P
1O
1U
0W
0V
0A
1>
1=
0<
0I
0G
0F
0E
0D
#85000
1*
14
1Q
1W
0H
1E
1D
0C
#86000
0*
1)
04
13
0Q
1P
0W
1V
1I
0E
0D
#87000
1*
14
1Q
1W
1H
1G
1F
1E
1D
1C
#88000
0*
0)
0(
1'
04
03
02
11
0Q
0P
0O
1N
0U
1T
0W
0V
1B
0>
0=
0I
0G
0F
0E
0D
#89000
1*
14
1Q
1W
0H
1E
1D
0C
#90000
0*
1)
04
13
0Q
1P
0W
1V
1I
0E
0D
#91000
1*
14
1Q
1W
1H
1G
1F
1E
1D
1C
#92000
0*
0)
1(
04
03
12
0Q
0P
1O
1U
0W
0V
1A
1@
1?
1>
1=
1<
0I
0G
0F
0E
0D
#93000
1*
14
1Q
1W
0H
1E
1D
0C
#94000
0*
1)
04
13
0Q
1P
0W
1V
1I
0E
0D
#95000
1*
14
1Q
1W
1H
1G
1F
1E
1D
1C
#96000
0*
0)
0(
0'
0&
1%
04
03
02
01
00
1/
0Q
0P
0O
0N
0M
1L
0S
1R
0U
0T
0W
0V
1;
07
06
0B
0@
0?
0>
0=
0I
0G
0F
0E
0D
#97000
1*
14
1Q
1W
0H
1E
1D
0C
#98000
0*
1)
04
13
0Q
1P
0W
1V
1I
0E
0D
#99000
1*
14
1Q
1W
1H
1G
1F
1E
1D
1C
#100000
0*
0)
1(
04
03
12
0Q
0P
1O
1U
0W
0V
0A
1>
1=
0<
0I
0G
0F
0E
0D
#101000
1*
14
1Q
1W
0H
1E
1D
0C
#102000
0*
1)
04
13
0Q
1P
0W
1V
1I
0E
0D
#103000
1*
14
1Q
1W
1H
1G
1F
1E
1D
1C
#104000
0*
0)
0(
1'
04
03
02
11
0Q
0P
0O
1N
0U
1T
0W
0V
1B
0>
0=
0I
0G
0F
0E
0D
#105000
1*
14
1Q
1W
0H
1E
1D
0C
#106000
0*
1)
04
13
0Q
1P
0W
1V
1I
0E
0D
#107000
1*
14
1Q
1W
1H
1G
1F
1E
1D
1C
#108000
0*
0)
1(
04
03
12
0Q
0P
1O
1U
0W
0V
1A
1@
1?
1>
1=
1<
0I
0G
0F
0E
0D
#109000
1*
14
1Q
1W
0H
1E
1D
0C
#110000
0*
1)
04
13
0Q
1P
0W
1V
1I
0E
0D
#111000
1*
14
1Q
1W
1H
1G
1F
1E
1D
1C
#112000
0*
0)
0(
0'
1&
04
03
02
01
10
0Q
0P
0O
0N
1M
1S
0U
0T
0W
0V
1:
19
18
17
16
15
0B
0@
0?
0>
0=
0I
0G
0F
0E
0D
#113000
1*
14
1Q
1W
0H
1E
1D
0C
#114000
0*
1)
04
13
0Q
1P
0W
1V
1I
0E
0D
#115000
1*
14
1Q
1W
1H
1G
1F
1E
1D
1C
#116000
0*
0)
1(
04
03
12
0Q
0P
1O
1U
0W
0V
0A
1>
1=
0<
0I
0G
0F
0E
0D
#117000
1*
14
1Q
1W
0H
1E
1D
0C
#118000
0*
1)
04
13
0Q
1P
0W
1V
1I
0E
0D
#119000
1*
14
1Q
1W
1H
1G
1F
1E
1D
1C
#120000
0*
0)
0(
1'
04
03
02
11
0Q
0P
0O
1N
0U
1T
0W
0V
1B
0>
0=
0I
0G
0F
0E
0D
#121000
1*
14
1Q
1W
0H
1E
1D
0C
#122000
0*
1)
04
13
0Q
1P
0W
1V
1I
0E
0D
#123000
1*
14
1Q
1W
1H
1G
1F
1E
1D
1C
#124000
0*
0)
1(
04
03
12
0Q
0P
1O
1U
0W
0V
1A
1@
1?
1>
1=
1<
0I
0G
0F
0E
0D
#125000
1*
14
1Q
1W
0H
1E
1D
0C
#126000
0*
1)
04
13
0Q
1P
0W
1V
1I
0E
0D
#127000
1*
14
1Q
1W
1H
1G
1F
1E
1D
1C
#128000
0*
0)
0(
0'
0&
0%
0$
1#
04
03
02
01
00
0/
0.
1-
0Q
0P
0O
0N
0M
0L
0S
0R
0U
0T
0W
0V
0;
09
08
07
06
0B
0@
0?
0>
0=
0I
0G
0F
0E
0D
#129000
1*
14
1Q
1W
0H
1E
1D
0C
#130000
0*
1)
04
13
0Q
1P
0W
1V
1I
0E
0D
#131000
1*
14
1Q
1W
1H
1G
1F
1E
1D
1C
#132000
0*
0)
1(
04
03
12
0Q
0P
1O
1U
0W
0V
0A
1>
1=
0<
0I
0G
0F
0E
0D
#133000
1*
14
1Q
1W
0H
1E
1D
0C
#134000
0*
1)
04
13
0Q
1P
0W
1V
1I
0E
0D
#135000
1*
14
1Q
1W
1H
1G
1F
1E
1D
1C
#136000
0*
0)
0(
1'
04
03
02
11
0Q
0P
0O
1N
0U
1T
0W
0V
1B
0>
0=
0I
0G
0F
0E
0D
#137000
1*
14
1Q
1W
0H
1E
1D
0C
#138000
0*
1)
04
13
0Q
1P
0W
1V
1I
0E
0D
#139000
1*
14
1Q
1W
1H
1G
1F
1E
1D
1C
#140000
0*
0)
1(
04
03
12
0Q
0P
1O
1U
0W
0V
1A
1@
1?
1>
1=
1<
0I
0G
0F
0E
0D
#141000
1*
14
1Q
1W
0H
1E
1D
0C
#142000
0*
1)
04
13
0Q
1P
0W
1V
1I
0E
0D
#143000
1*
14
1Q
1W
1H
1G
1F
1E
1D
1C
#144000
0*
0)
0(
0'
1&
04
03
02
01
10
0Q
0P
0O
0N
1M
1S
0U
0T
0W
0V
0:
17
16
05
0B
0@
0?
0>
0=
0I
0G
0F
0E
0D
#145000
1*
14
1Q
1W
0H
1E
1D
0C
#146000
0*
1)
04
13
0Q
1P
0W
1V
1I
0E
0D
#147000
1*
14
1Q
1W
1H
1G
1F
1E
1D
1C
#148000
0*
0)
1(
04
03
12
0Q
0P
1O
1U
0W
0V
0A
1>
1=
0<
0I
0G
0F
0E
0D
#149000
1*
14
1Q
1W
0H
1E
1D
0C
#150000
0*
1)
04
13
0Q
1P
0W
1V
1I
0E
0D
#151000
1*
14
1Q
1W
1H
1G
1F
1E
1D
1C
#152000
0*
0)
0(
1'
04
03
02
11
0Q
0P
0O
1N
0U
1T
0W
0V
1B
0>
0=
0I
0G
0F
0E
0D
#153000
1*
14
1Q
1W
0H
1E
1D
0C
#154000
0*
1)
04
13
0Q
1P
0W
1V
1I
0E
0D
#155000
1*
14
1Q
1W
1H
1G
1F
1E
1D
1C
#156000
0*
0)
1(
04
03
12
0Q
0P
1O
1U
0W
0V
1A
1@
1?
1>
1=
1<
0I
0G
0F
0E
0D
#157000
1*
14
1Q
1W
0H
1E
1D
0C
#158000
0*
1)
04
13
0Q
1P
0W
1V
1I
0E
0D
#159000
1*
14
1Q
1W
1H
1G
1F
1E
1D
1C
#160000
0*
0)
0(
0'
0&
1%
04
03
02
01
00
1/
0Q
0P
0O
0N
0M
1L
0S
1R
0U
0T
0W
0V
1;
07
06
0B
0@
0?
0>
0=
0I
0G
0F
0E
0D
#161000
1*
14
1Q
1W
0H
1E
1D
0C
#162000
0*
1)
04
13
0Q
1P
0W
1V
1I
0E
0D
#163000
1*
14
1Q
1W
1H
1G
1F
1E
1D
1C
#164000
0*
0)
1(
04
03
12
0Q
0P
1O
1U
0W
0V
0A
1>
1=
0<
0I
0G
0F
0E
0D
#165000
1*
14
1Q
1W
0H
1E
1D
0C
#166000
0*
1)
04
13
0Q
1P
0W
1V
1I
0E
0D
#167000
1*
14
1Q
1W
1H
1G
1F
1E
1D
1C
#168000
0*
0)
0(
1'
04
03
02
11
0Q
0P
0O
1N
0U
1T
0W
0V
1B
0>
0=
0I
0G
0F
0E
0D
#169000
1*
14
1Q
1W
0H
1E
1D
0C
#170000
0*
1)
04
13
0Q
1P
0W
1V
1I
0E
0D
#171000
1*
14
1Q
1W
1H
1G
1F
1E
1D
1C
#172000
0*
0)
1(
04
03
12
0Q
0P
1O
1U
0W
0V
1A
1@
1?
1>
1=
1<
0I
0G
0F
0E
0D
#173000
1*
14
1Q
1W
0H
1E
1D
0C
#174000
0*
1)
04
13
0Q
1P
0W
1V
1I
0E
0D
#175000
1*
14
1Q
1W
1H
1G
1F
1E
1D
1C
#176000
0*
0)
0(
0'
1&
04
03
02
01
10
0Q
0P
0O
0N
1M
1S
0U
0T
0W
0V
1:
19
18
17
16
15
0B
0@
0?
0>
0=
0I
0G
0F
0E
0D
#177000
1*
14
1Q
1W
0H
1E
1D
0C
#178000
0*
1)
04
13
0Q
1P
0W
1V
1I
0E
0D
#179000
1*
14
1Q
1W
1H
1G
1F
1E
1D
1C
#180000
0*
0)
1(
04
03
12
0Q
0P
1O
1U
0W
0V
0A
1>
1=
0<
0I
0G
0F
0E
0D
#181000
1*
14
1Q
1W
0H
1E
1D
0C
#182000
0*
1)
04
13
0Q
1P
0W
1V
1I
0E
0D
#183000
1*
14
1Q
1W
1H
1G
1F
1E
1D
1C
#184000
0*
0)
0(
1'
04
03
02
11
0Q
0P
0O
1N
0U
1T
0W
0V
1B
0>
0=
0I
0G
0F
0E
0D
#185000
1*
14
1Q
1W
0H
1E
1D
0C
#186000
0*
1)
04
13
0Q
1P
0W
1V
1I
0E
0D
#187000
1*
14
1Q
1W
1H
1G
1F
1E
1D
1C
#188000
0*
0)
1(
04
03
12
0Q
0P
1O
1U
0W
0V
1A
1@
1?
1>
1=
1<
0I
0G
0F
0E
0D
#189000
1*
14
1Q
1W
0H
1E
1D
0C
#190000
0*
1)
04
13
0Q
1P
0W
1V
1I
0E
0D
#191000
1*
14
1Q
1W
1H
1G
1F
1E
1D
1C
#192000
0*
0)
0(
0'
0&
0%
1$
04
03
02
01
00
0/
1.
0Q
0P
0O
0N
0M
0L
0S
0R
0U
0T
0W
0V
0;
09
08
07
06
0B
0@
0?
0>
0=
0I
0G
0F
0E
0D
#193000
1*
14
1Q
1W
0H
1E
1D
0C
#194000
0*
1)
04
13
0Q
1P
0W
1V
1I
0E
0D
#195000
1*
14
1Q
1W
1H
1G
1F
1E
1D
1C
#196000
0*
0)
1(
04
03
12
0Q
0P
1O
1U
0W
0V
0A
1>
1=
0<
0I
0G
0F
0E
0D
#197000
1*
14
1Q
1W
0H
1E
1D
0C
#198000
0*
1)
04
13
0Q
1P
0W
1V
1I
0E
0D
#199000
1*
14
1Q
1W
1H
1G
1F
1E
1D
1C
#200000
0*
0)
0(
1'
04
03
02
11
0Q
0P
0O
1N
0U
1T
0W
0V
1B
0>
0=
0I
0G
0F
0E
0D
#201000
1*
14
1Q
1W
0H
1E
1D
0C
#202000
0*
1)
04
13
0Q
1P
0W
1V
1I
0E
0D
#203000
1*
14
1Q
1W
1H
1G
1F
1E
1D
1C
#204000
0*
0)
1(
04
03
12
0Q
0P
1O
1U
0W
0V
1A
1@
1?
1>
1=
1<
0I
0G
0F
0E
0D
#205000
1*
14
1Q
1W
0H
1E
1D
0C
#206000
0*
1)
04
13
0Q
1P
0W
1V
1I
0E
0D
#207000
1*
14
1Q
1W
1H
1G
1F
1E
1D
1C
#208000
0*
0)
0(
0'
1&
04
03
02
01
10
0Q
0P
0O
0N
1M
1S
0U
0T
0W
0V
0:
17
16
05
0B
0@
0?
0>
0=
0I
0G
0F
0E
0D
#209000
1*
14
1Q
1W
0H
1E
1D
0C
#210000
0*
1)
04
13
0Q
1P
0W
1V
1I
0E
0D
#211000
1*
14
1Q
1W
1H
1G
1F
1E
1D
1C
#212000
0*
0)
1(
04
03
12
0Q
0P
1O
1U
0W
0V
0A
1>
1=
0<
0I
0G
0F
0E
0D
#213000
1*
14
1Q
1W
0H
1E
1D
0C
#214000
0*
1)
04
13
0Q
1P
0W
1V
1I
0E
0D
#215000
1*
14
1Q
1W
1H
1G
1F
1E
1D
1C
#216000
0*
0)
0(
1'
04
03
02
11
0Q
0P
0O
1N
0U
1T
0W
0V
1B
0>
0=
0I
0G
0F
0E
0D
#217000
1*
14
1Q
1W
0H
1E
1D
0C
#218000
0*
1)
04
13
0Q
1P
0W
1V
1I
0E
0D
#219000
1*
14
1Q
1W
1H
1G
1F
1E
1D
1C
