tarefa1/part3.vhd
library ieee;
use ieee.std_logic_1164.all;

-- MUX 4:1 de 2 bits

entity part3 is
    port (
        SW   : in  std_logic_vector(9 downto 0);
        LEDG : out std_logic_vector(9 downto 0)
    );
end part3;

-- process combinacional com case

architecture behavioral of part3 is
begin
    process (SW)
    begin
        LEDG <= (others => '0');

        case SW(9 downto 8) is
            when "00"   => LEDG(1 downto 0) <= SW(1 downto 0);
            when "01"   => LEDG(1 downto 0) <= SW(3 downto 2);
            when "10"   => LEDG(1 downto 0) <= SW(5 downto 4);
            when "11"   => LEDG(1 downto 0) <= SW(7 downto 6);
            when others => null;
        end case;
    end process;
end behavioral;

tarefa1/part3_tb.vhd
library ieee;
use ieee.std_logic_1164.all;
use ieee.numeric_std.all;

entity part3_tb is
end part3_tb;

architecture test of part3_tb is
    signal SW   : std_logic_vector(9 downto 0) := (others => '0');
    signal LEDG : std_logic_vector(9 downto 0);
begin
    dut : entity work.part3(behavioral)
        port map (
            SW   => SW,
            LEDG => LEDG
        );

    stimulus : process
        variable switches : std_logic_vector(9 downto 0);
        variable expected : std_logic_vector(1 downto 0);
    begin
        for selector in 0 to 3 loop
            for inputs in 0 to 255 loop
                switches := (others => '0');
                switches(9 downto 8) := std_logic_vector(to_unsigned(selector, 2));
                switches(7 downto 0) := std_logic_vector(to_unsigned(inputs, 8));

                case selector is
                    when 0      => expected := switches(1 downto 0);
                    when 1      => expected := switches(3 downto 2);
                    when 2      => expected := switches(5 downto 4);
                    when others => expected := switches(7 downto 6);
                end case;

                SW <= switches;
                wait for 1 ns;

                assert LEDG(1 downto 0) = expected
                    report "MUX selecionou a entrada incorreta" severity error;
                assert LEDG(9 downto 2) = "00000000"
                    report "LEDs nao utilizados deveriam estar apagados" severity error;
            end loop;
        end loop;

        report "Parte 3: 1024 casos aprovados" severity note;
        wait;
    end process;
end test;

tarefa1/part3.vcd
$date
	Mon Sep 14 18:18:14 2026
$end
$version
	ModelSim Version 10.1d
$end
$timescale
	1ps
$end
$scope module part3_tb $end
$var wire 1 ! SW [9] $end
$var wire 1 " SW [8] $end
$var wire 1 # SW [7] $end
$var wire 1 $ SW [6] $end
$var wire 1 % SW [5] $end
$var wire 1 & SW [4] $end
$var wire 1 ' SW [3] $end
$var wire 1 ( SW [2] $end
$var wire 1 ) SW [1] $end
$var wire 1 * SW [0] $end
$var wire 1 + LEDG [9] $end
$var wire 1 , LEDG [8] $end
$var wire 1 - LEDG [7] $end
$var wire 1 . LEDG [6] $end
$var wire 1 / LEDG [5] $end
$var wire 1 0 LEDG [4] $end
$var wire 1 1 LEDG [3] $end
$var wire 1 2 LEDG [2] $end
$var wire 1 3 LEDG [1] $end
$var wire 1 4 LEDG [0] $end
$scope module dut $end
$var wire 1 ! SW [9] $end
$var wire 1 " SW [8] $end
$var wire 1 # SW [7] $end
$var wire 1 $ SW [6] $end
$var wire 1 % SW [5] $end
$var wire 1 & SW [4] $end
$var wire 1 ' SW [3] $end
$var wire 1 ( SW [2] $end
$var wire 1 ) SW [1] $end
$var wire 1 * SW [0] $end
$var wire 1 + LEDG [9] $end
$var wire 1 , LEDG [8] $end
$var wire 1 - LEDG [7] $end
$var wire 1 . LEDG [6] $end
$var wire 1 / LEDG [5] $end
$var wire 1 0 LEDG [4] $end
$var wire 1 1 LEDG [3] $end
$var wire 1 2 LEDG [2] $end
$var wire 1 3 LEDG [1] $end
$var wire 1 4 LEDG [0] $end
$upscope $end
$upscope $end
$enddefinitions $end
#0
$dumpvars
0+
0,
0-
0.
0/
00
01
02
03
04
0!
0"
0#
0$
0%
0&
0'
0(
0)
0*
$end
#1000
1*
14
#2000
0*
1)
13
04
#3000
1*
14
#4000
0*
0)
1(
04
03
#5000
1*
14
#6000
0*
1)
13
04
#7000
1*
14
#8000
0*
0)
0(
1'
04
03
#9000
1*
14
#10000
0*
1)
13
04
#11000
1*
14
#12000
0*
0)
1(
04
03
#13000
1*
14
#14000
0*
1)
13
04
#15000
1*
14
#16000
0*
0)
0(
0'
1&
04
03
#17000
1*
14
#18000
0*
1)
13
04
#19000
1*
14
#20000
0*
0)
1(
04
03
#21000
1*
14
#22000
0*
1)
13
04
#23000
1*
14
#24000
0*
0)
0(
1'
04
03
#25000
1*
14
#26000
0*
1)
13
04
#27000
1*
14
#28000
0*
0)
1(
04
03
#29000
1*
14
#30000
0*
1)
13
04
#31000
1*
14
#32000
0*
0)
0(
0'
0&
1%
04
03
#33000
1*
14
#34000
0*
1)
13
04
#35000
1*
14
#36000
0*
0)
1(
04
03
#37000
1*
14
#38000
0*
1)
13
04
#39000
1*
14
#40000
0*
0)
0(
1'
04
03
#41000
1*
14
#42000
0*
1)
13
04
#43000
1*
14
#44000
0*
0)
1(
04
03
#45000
1*
14
#46000
0*
1)
13
04
#47000
1*
14
#48000
0*
0)
0(
0'
1&
04
03
#49000
1*
14
#50000
0*
1)
13
04
#51000
1*
14
#52000
0*
0)
1(
04
03
#53000
1*
14
#54000
0*
1)
13
04
#55000
1*
14
#56000
0*
0)
0(
1'
04
03
#57000
1*
14
#58000
0*
1)
13
04
#59000
1*
14
#60000
0*
0)
1(
04
03
#61000
1*
14
#62000
0*
1)
13
04
#63000
1*
14
#64000
0*
0)
0(
0'
0&
0%
1$
04
03
#65000
1*
14
#66000
0*
1)
13
04
#67000
1*
14
#68000
0*
0)
1(
04
03
#69000
1*
14
#70000
0*
1)
13
04
#71000
1*
14
#72000
0*
0)
0(
1'
04
03
#73000
1*
14
#74000
0*
1)
13
04
#75000
1*
14
#76000
0*
0)
1(
04
03
#77000
1*
14
#78000
0*
1)
13
04
#79000
1*
14
#80000
0*
0)
0(
0'
1&
04
03
#81000
1*
14
#82000
0*
1)
13
04
#83000
1*
14
#84000
0*
0)
1(
04
03
#85000
1*
14
#86000
0*
1)
13
04
#87000
1*
14
#88000
0*
0)
0(
1'
04
03
#89000
1*
14
#90000
0*
1)
13
04
#91000
1*
14
#92000
0*
0)
1(
04
03
#93000
1*
14
#94000
0*
1)
13
04
#95000
1*
14
#96000
0*
0)
0(
0'
0&
1%
04
03
#97000
1*
14
#98000
0*
1)
13
04
#99000
1*
14
#100000
0*
0)
1(
04
03
#101000
1*
14
#102000
0*
1)
13
04
#103000
1*
14
#104000
0*
0)
0(
1'
04
03
#105000
1*
14
#106000
0*
1)
13
04
#107000
1*
14
#108000
0*
0)
1(
04
03
#109000
1*
14
#110000
0*
1)
13
04
#111000
1*
14
#112000
0*
0)
0(
0'
1&
04
03
#113000
1*
14
#114000
0*
1)
13
04
#115000
1*
14
#116000
0*
0)
1(
04
03
#117000
1*
14
#118000
0*
1)
13
04
#119000
1*
14
#120000
0*
0)
0(
1'
04
03
#121000
1*
14
#122000
0*
1)
13
04
#123000
1*
14
#124000
0*
0)
1(
04
03
#125000
1*
14
#126000
0*
1)
13
04
#127000
1*
14
#128000
0*
0)
0(
0'
0&
0%
0$
1#
04
03
#129000
1*
14
#130000
0*
1)
13
04
#131000
1*
14
#132000
0*
0)
1(
04
03
#133000
1*
14
#134000
0*
1)
13
04
#135000
1*
14
#136000
0*
0)
0(
1'
04
03
#137000
1*
14
#138000
0*
1)
13
04
#139000
1*
14
#140000
0*
0)
1(
04
03
#141000
1*
14
#142000
0*
1)
13
04
#143000
1*
14
#144000
0*
0)
0(
0'
1&
04
03
#145000
1*
14
#146000
0*
1)
13
04
#147000
1*
14
#148000
0*
0)
1(
04
03
#149000
1*
14
#150000
0*
1)
13
04
#151000
1*
14
#152000
0*
0)
0(
1'
04
03
#153000
1*
14
#154000
0*
1)
13
04
#155000
1*
14
#156000
0*
0)
1(
04
03
#157000
1*
14
#158000
0*
1)
13
04
#159000
1*
14
#160000
0*
0)
0(
0'
0&
1%
04
03
#161000
1*
14
#162000
0*
1)
13
04
#163000
1*
14
#164000
0*
0)
1(
04
03
#165000
1*
14
#166000
0*
1)
13
04
#167000
1*
14
#168000
0*
0)
0(
1'
04
03
#169000
1*
14
#170000
0*
1)
13
04
#171000
1*
14
#172000
0*
0)
1(
04
03
#173000
1*
14
#174000
0*
1)
13
04
#175000
1*
14
#176000
0*
0)
0(
0'
1&
04
03
#177000
1*
14
#178000
0*
1)
13
04
#179000
1*
14
#180000
0*
0)
1(
04
03
#181000
1*
14
#182000
0*
1)
13
04
#183000
1*
14
#184000
0*
0)
0(
1'
04
03
#185000
1*
14
#186000
0*
1)
13
04
#187000
1*
14
#188000
0*
0)
1(
04
03
#189000
1*
14
#190000
0*
1)
13
04
#191000
1*
14
#192000
0*
0)
0(
0'
0&
0%
1$
04
03
#193000
1*
14
#194000
0*
1)
13
04
#195000
1*
14
#196000
0*
0)
1(
04
03
#197000
1*
14
#198000
0*
1)
13
04
#199000
1*
14
#200000
0*
0)
0(
1'
04
03
#201000
1*
14
#202000
0*
1)
13
04
#203000
1*
14
#204000
0*
0)
1(
04
03
#205000
1*
14
#206000
0*
1)
13
04
#207000
1*
14
#208000
0*
0)
0(
0'
1&
04
03
#209000
1*
14
#210000
0*
1)
13
04
#211000
1*
14
#212000
0*
0)
1(
04
03
#213000
1*
14
#214000
0*
1)
13
04
#215000
1*
14
#216000
0*
0)
0(
1'
04
03
#217000
1*
14
#218000
0*
1)
13
04
#219000
1*
14
#220000
0*
0)
1(
04
03
#221000
1*
14
#222000
0*
1)
13
04
#223000
1*
14
#224000
0*
0)
0(
0'
0&
1%
04
03
#225000
1*
14
#226000
0*
1)
13
04
#227000
1*
14
#228000
0*
0)
1(
04
03
#229000
1*
14
#230000
0*
1)
13
04
#231000
1*
14
#232000
0*
0)
0(
1'
04
03
#233000
1*
14
#234000
0*
1)
13
04
#235000
1*
14
#236000
0*
0)
1(
04
03
#237000
1*
14
#238000
0*
1)
13
04
#239000
1*
14
#240000
0*
0)
0(
0'
1&
04
03
#241000
1*
14
#242000
0*
1)
13
04
#243000
1*
14
#244000
0*
0)
1(
04
03
#245000
1*
14
#246000
0*
1)
13
04
#247000
1*
14
#248000
0*
0)
0(
1'
04
03
#249000
1*
14
#250000
0*
1)
13
04
#251000
1*
14
#252000
0*
0)
1(
04
03
#253000
1*
14
#254000
0*
1)
13
04
#255000
1*
14
#256000
0*
0)
0(
0'
0&
0%
0$
0#
1"
04
03
#257000
1*
#258000
0*
1)
#259000
1*
#260000
0*
0)
1(
14
#261000
1*
#262000
0*
1)
#263000
1*
#264000
0*
0)
0(
1'
13
04
#265000
1*
#266000
0*
1)
#267000
1*
#268000
0*
0)
1(
14
#269000
1*
#270000
0*
1)
#271000
1*
#272000
0*
0)
0(
0'
1&
04
03
#273000
1*
#274000
0*
1)
#275000
1*
#276000
0*
0)
1(
14
#277000
1*
#278000
0*
1)
#279000
1*
#280000
0*
0)
0(
1'
13
04
#281000
1*
#282000
0*
1)
#283000
1*
#284000
0*
0)
1(
14
#285000
1*
#286000
0*
1)
#287000
1*
#288000
0*
0)
0(
0'
0&
1%
04
03
#289000
1*
#290000
0*
1)
#291000
1*
#292000
0*
0)
1(
14
#293000
1*
#294000
0*
1)
#295000
1*
#296000
0*
0)
0(
1'
13
04
#297000
1*
#298000
0*
1)
#299000
1*
#300000
0*
0)
1(
14
#301000
1*
#302000
0*
1)
#303000
1*
#304000
0*
0)
0(
0'
1&
04
03
#305000
1*
#306000
0*
1)
#307000
1*
#308000
0*
0)
1(
14
#309000
1*
#310000
0*
1)
#311000
1*
#312000
0*
0)
0(
1'
13
04
#313000
1*
#314000
0*
1)
#315000
1*
#316000
0*
0)
1(
14
#317000
1*
#318000
0*
1)
#319000
1*
#320000
0*
0)
0(
0'
0&
0%
1$
04
03
#321000
1*
#322000
0*
1)
#323000
1*
#324000
0*
0)
1(
14
#325000
1*
#326000
0*
1)
#327000
1*
#328000
0*
0)
0(
1'
13
04
#329000
1*
#330000
0*
1)
#331000
1*
#332000
0*
0)
1(
14
#333000
1*
#334000
0*
1)
#335000
1*
#336000
0*
0)
0(
0'
1&
04
03
#337000
1*
#338000
0*
1)
#339000
1*
#340000
0*
0)
1(
14
#341000
1*
#342000
0*
1)
#343000
1*
#344000
0*
0)
0(
1'
13
04
#345000
1*
#346000
0*
1)
#347000
1*
#348000
0*
0)
1(
14
#349000
1*
#350000
0*
1)
#351000
1*
#352000
0*
0)
0(
0'
0&
1%
04
03
#353000
1*
#354000
0*
1)
#355000
1*
#356000
0*
0)
1(
14
#357000
1*
#358000
0*
1)
#359000
1*
#360000
0*
0)
0(
1'
13
04
#361000
1*
#362000
0*
1)
#363000
1*
#364000
0*
0)
1(
14
#365000
1*
#366000
0*
1)
#367000
1*
#368000
0*
0)
0(
0'
1&
04
03
#369000
1*
#370000
0*
1)
#371000
1*
#372000
0*
0)
1(
14
#373000
1*
#374000
0*
1)
#375000
1*
#376000
0*
0)
0(
1'
13
04
#377000
1*
#378000
0*
1)
#379000
1*
#380000
0*
0)
1(
14
#381000
1*
#382000
0*
1)
#383000
1*
#384000
0*
0)
0(
0'
0&
0%
0$
1#
04
03
#385000
1*
#386000
0*
1)
#387000
1*
#388000
0*
0)
1(
14
#389000
1*
#390000
0*
1)
#391000
1*
#392000
0*
0)
0(
1'
13
04
#393000
1*
#394000
0*
1)
#395000
1*
#396000
0*
0)
1(
14
#397000
1*
#398000
0*
1)
#399000
1*
#400000
0*
0)
0(
0'
1&
04
03
#401000
1*
#402000
0*
1)
#403000
1*
#404000
0*
0)
1(
14
#405000
1*
#406000
0*
1)
#407000
1*
#408000
0*
0)
0(
1'
13
04
#409000
1*
#410000
0*
1)
#411000
1*
#412000
0*
0)
1(
14
#413000
1*
#414000
0*
1)
#415000
1*
#416000
0*
0)
0(
0'
0&
1%
04
03
#417000
1*
#418000
0*
1)
#419000
1*
#420000
0*
0)
1(
14
#421000
1*
#422000
0*
1)
#423000
1*
#424000
0*
0)
0(
1'
13
04
#425000
1*
#426000
0*
1)
#427000
1*
#428000
0*
0)
1(
14
#429000
1*
#430000
0*
1)
#431000
1*
#432000
0*
0)
0(
0'
1&
04
03
#433000
1*
#434000
0*
1)
#435000
1*
#436000
0*
0)
1(
14
#437000
1*
#438000
0*
1)
#439000
1*
#440000
0*
0)
0(
1'
13
04
#441000
1*
#442000
0*
1)
#443000
1*
#444000
0*
0)
1(
14
#445000
1*
#446000
0*
1)
#447000
1*
#448000
0*
0)
0(
0'
0&
0%
1$
04
03
#449000
1*
#450000
0*
1)
#451000
1*
#452000
0*
0)
1(
14
#453000
1*
#454000
0*
1)
#455000
1*
#456000
0*
0)
0(
1'
13
04
#457000
1*
#458000
0*
1)
#459000
1*
#460000
0*
0)
1(
14
#461000
1*
#462000
0*
1)
#463000
1*
#464000
0*
0)
0(
0'
1&
04
03
#465000
1*
#466000
0*
1)
#467000
1*
#468000
0*
0)
1(
14
#469000
1*
#470000
0*
1)
#471000
1*
#472000
0*
0)
0(
1'
13
04
#473000
1*
#474000
0*
1)
#475000
1*
#476000
0*
0)
1(
14
#477000
1*
#478000
0*
1)
#479000
1*
#480000
0*
0)
0(
0'
0&
1%
04
03
#481000
1*
#482000
0*
1)
#483000
1*
#484000
0*
0)
1(
14
#485000
1*
#486000
0*
1)
#487000
1*
#488000
0*
0)
0(
1'
13
04
#489000
1*
#490000
0*
1)
#491000
1*
#492000
0*
0)
1(
14
#493000
1*
#494000
0*
1)
#495000
1*
#496000
0*
0)
0(
0'
1&
04
03
#497000
1*
#498000
0*
1)
#499000
1*
#500000
0*
0)
1(
14
#501000
1*
#502000
0*
1)
#503000
1*
#504000
0*
0)
0(
1'
13
04
#505000
1*
#506000
0*
1)
#507000
1*
#508000
0*
0)
1(
14
#509000
1*
#510000
0*
1)
#511000
1*
#512000
0*
0)
0(
0'
0&
0%
0$
0#
0"
1!
04
03
#513000
1*
#514000
0*
1)
#515000
1*
#516000
0*
0)
1(
#517000
1*
#518000
0*
1)
#519000
1*
#520000
0*
0)
0(
1'
#521000
1*
#522000
0*
1)
#523000
1*
#524000
0*
0)
1(
#525000
1*
#526000
0*
1)
#527000
1*
#528000
0*
0)
0(
0'
1&
14
#529000
1*
#530000
0*
1)
#531000
1*
#532000
0*
0)
1(
#533000
1*
#534000
0*
1)
#535000
1*
#536000
0*
0)
0(
1'
#537000
1*
#538000
0*
1)
#539000
1*
#540000
0*
0)
1(
#541000
1*
#542000
0*
1)
#543000
1*
#544000
0*
0)
0(
0'
0&
1%
13
04
#545000
1*
#546000
0*
1)
#547000
1*
#548000
0*
0)
1(
#549000
1*
#550000
0*
1)
#551000
1*
#552000
0*
0)
0(
1'
#553000
1*
#554000
0*
1)
#555000
1*
#556000
0*
0)
1(
#557000
1*
#558000
0*
1)
#559000
1*
#560000
0*
0)
0(
0'
1&
14
#561000
1*
#562000
0*
1)
#563000
1*
#564000
0*
0)
1(
#565000
1*
#566000
0*
1)
#567000
1*
#568000
0*
0)
0(
1'
#569000
1*
#570000
0*
1)
#571000
1*
#572000
0*
0)
1(
#573000
1*
#574000
0*
1)
#575000
1*
#576000
0*
0)
0(
0'
0&
0%
1$
04
03
#577000
1*
#578000
0*
1)
#579000
1*
#580000
0*
0)
1(
#581000
1*
#582000
0*
1)
#583000
1*
#584000
0*
0)
0(
1'
#585000
1*
#586000
0*
1)
#587000
1*
#588000
0*
0)
1(
#589000
1*
#590000
0*
1)
#591000
1*
#592000
0*
0)
0(
0'
1&
14
#593000
1*
#594000
0*
1)
#595000
1*
#596000
0*
0)
1(
#597000
1*
#598000
0*
1)
#599000
1*
#600000
0*
0)
0(
1'
#601000
1*
#602000
0*
1)
#603000
1*
#604000
0*
0)
1(
#605000
1*
#606000
0*
1)
#607000
1*
#608000
0*
0)
0(
0'
0&
1%
13
04
#609000
1*
#610000
0*
1)
#611000
1*
#612000
0*
0)
1(
#613000
1*
#614000
0*
1)
#615000
1*
#616000
0*
0)
0(
1'
#617000
1*
#618000
0*
1)
#619000
1*
#620000
0*
0)
1(
#621000
1*
#622000
0*
1)
#623000
1*
#624000
0*
0)
0(
0'
1&
14
#625000
1*
#626000
0*
1)
#627000
1*
#628000
0*
0)
1(
#629000
1*
#630000
0*
1)
#631000
1*
#632000
0*
0)
0(
1'
#633000
1*
#634000
0*
1)
#635000
1*
#636000
0*
0)
1(
#637000
1*
#638000
0*
1)
#639000
1*
#640000
0*
0)
0(
0'
0&
0%
0$
1#
04
03
#641000
1*
#642000
0*
1)
#643000
1*
#644000
0*
0)
1(
#645000
1*
#646000
0*
1)
#647000
1*
#648000
0*
0)
0(
1'
#649000
1*
#650000
0*
1)
#651000
1*
#652000
0*
0)
1(
#653000
1*
#654000
0*
1)
#655000
1*
#656000
0*
0)
0(
0'
1&
14
#657000
1*
#658000
0*
1)
#659000
1*
#660000
0*
0)
1(
#661000
1*
#662000
0*
1)
#663000
1*
#664000
0*
0)
0(
1'
#665000
1*
#666000
0*
1)
#667000
1*
#668000
0*
0)
1(
#669000
1*
#670000
0*
1)
#671000
1*
#672000
0*
0)
0(
0'
0&
1%
13
04
#673000
1*
#674000
0*
1)
#675000
1*
#676000
0*
0)
1(
#677000
1*
#678000
0*
1)
#679000
1*
#680000
0*
0)
0(
1'
#681000
1*
#682000
0*
1)
#683000
1*
#684000
0*
0)
1(
#685000
1*
#686000
0*
1)
#687000
1*
#688000
0*
0)
0(
0'
1&
14
#689000
1*
#690000
0*
1)
#691000
1*
#692000
0*
0)
1(
#693000
1*
#694000
0*
1)
#695000
1*
#696000
0*
0)
0(
1'
#697000
1*
#698000
0*
1)
#699000
1*
#700000
0*
0)
1(
#701000
1*
#702000
0*
1)
#703000
1*
#704000
0*
0)
0(
0'
0&
0%
1$
04
03
#705000
1*
#706000
0*
1)
#707000
1*
#708000
0*
0)
1(
#709000
1*
#710000
0*
1)
#711000
1*
#712000
0*
0)
0(
1'
#713000
1*
#714000
0*
1)
#715000
1*
#716000
0*
0)
1(
#717000
1*
#718000
0*
1)
#719000
1*
#720000
0*
0)
0(
0'
1&
14
#721000
1*
#722000
0*
1)
#723000
1*
#724000
0*
0)
1(
#725000
1*
#726000
0*
1)
#727000
1*
#728000
0*
0)
0(
1'
#729000
1*
#730000
0*
1)
#731000
1*
#732000
0*
0)
1(
#733000
1*
#734000
0*
1)
#735000
1*
#736000
0*
0)
0(
0'
0&
1%
13
04
#737000
1*
#738000
0*
1)
#739000
1*
#740000
0*
0)
1(
#741000
1*
#742000
0*
1)
#743000
1*
#744000
0*
0)
0(
1'
#745000
1*
#746000
0*
1)
#747000
1*
#748000
0*
0)
1(
#749000
1*
#750000
0*
1)
#751000
1*
#752000
0*
0)
0(
0'
1&
14
#753000
1*
#754000
0*
1)
#755000
1*
#756000
0*
0)
1(
#757000
1*
#758000
0*
1)
#759000
1*
#760000
0*
0)
0(
1'
#761000
1*
#762000
0*
1)
#763000
1*
#764000
0*
0)
1(
#765000
1*
#766000
0*
1)
#767000
1*
#768000
0*
0)
0(
0'
0&
0%
0$
0#
1"
04
03
#769000
1*
#770000
0*
1)
#771000
1*
#772000
0*
0)
1(
#773000
1*
#774000
0*
1)
#775000
1*
#776000
0*
0)
0(
1'
#777000
1*
#778000
0*
1)
#779000
1*
#780000
0*
0)
1(
#781000
1*
#782000
0*
1)
#783000
1*
#784000
0*
0)
0(
0'
1&
#785000
1*
#786000
0*
1)
#787000
1*
#788000
0*
0)
1(
#789000
1*
#790000
0*
1)
#791000
1*
#792000
0*
0)
0(
1'
#793000
1*
#794000
0*
1)
#795000
1*
#796000
0*
0)
1(
#797000
1*
#798000
0*
1)
#799000
1*
#800000
0*
0)
0(
0'
0&
1%
#801000
1*
#802000
0*
1)
#803000
1*
#804000
0*
0)
1(
#805000
1*
#806000
0*
1)
#807000
1*
#808000
0*
0)
0(
1'
#809000
1*
#810000
0*
1)
#811000
1*
#812000
0*
0)
1(
#813000
1*
#814000
0*
1)
#815000
1*
#816000
0*
0)
0(
0'
1&
#817000
1*
#818000
0*
1)
#819000
1*
#820000
0*
0)
1(
#821000
1*
#822000
0*
1)
#823000
1*
#824000
0*
0)
0(
1'
#825000
1*
#826000
0*
1)
#827000
1*
#828000
0*
0)
1(
#829000
1*
#830000
0*
1)
#831000
1*
#832000
0*
0)
0(
0'
0&
0%
1$
14
#833000
1*
#834000
0*
1)
#835000
1*
#836000
0*
0)
1(
#837000
1*
#838000
0*
1)
#839000
1*
#840000
0*
0)
0(
1'
#841000
1*
#842000
0*
1)
#843000
1*
#844000
0*
0)
1(
#845000
1*
#846000
0*
1)
#847000
1*
#848000
0*
0)
0(
0'
1&
#849000
1*
#850000
0*
1)
#851000
1*
#852000
0*
0)
1(
#853000
1*
#854000
0*
1)
#855000
1*
#856000
0*
0)
0(
1'
#857000
1*
#858000
0*
1)
#859000
1*
#860000
0*
0)
1(
#861000
1*
#862000
0*
1)
#863000
1*
#864000
0*
0)
0(
0'
0&
1%
#865000
1*
#866000
0*
1)
#867000
1*
#868000
0*
0)
1(
#869000
1*
#870000
0*
1)
#871000
1*
#872000
0*
0)
0(
1'
#873000
1*
#874000
0*
1)
#875000
1*
#876000
0*
0)
1(
#877000
1*
#878000
0*
1)
#879000
1*
#880000
0*
0)
0(
0'
1&
#881000
1*
#882000
0*
1)
#883000
1*
#884000
0*
0)
1(
#885000
1*
#886000
0*
1)
#887000
1*
#888000
0*
0)
0(
1'
#889000
1*
#890000
0*
1)
#891000
1*
#892000
0*
0)
1(
#893000
1*
#894000
0*
1)
#895000
1*
#896000
0*
0)
0(
0'
0&
0%
0$
1#
13
04
#897000
1*
#898000
0*
1)
#899000
1*
#900000
0*
0)
1(
#901000
1*
#902000
0*
1)
#903000
1*
#904000
0*
0)
0(
1'
#905000
1*
#906000
0*
1)
#907000
1*
#908000
0*
0)
1(
#909000
1*
#910000
0*
1)
#911000
1*
#912000
0*
0)
0(
0'
1&
#913000
1*
#914000
0*
1)
#915000
1*
#916000
0*
0)
1(
#917000
1*
#918000
0*
1)
#919000
1*
#920000
0*
0)
0(
1'
#921000
1*
#922000
0*
1)
#923000
1*
#924000
0*
0)
1(
#925000
1*
#926000
0*
1)
#927000
1*
#928000
0*
0)
0(
0'
0&
1%
#929000
1*
#930000
0*
1)
#931000
1*
#932000
0*
0)
1(
#933000
1*
#934000
0*
1)
#935000
1*
#936000
0*
0)
0(
1'
#937000
1*
#938000
0*
1)
#939000
1*
#940000
0*
0)
1(
#941000
1*
#942000
0*
1)
#943000
1*
#944000
0*
0)
0(
0'
1&
#945000
1*
#946000
0*
1)
#947000
1*
#948000
0*
0)
1(
#949000
1*
#950000
0*
1)
#951000
1*
#952000
0*
0)
0(
1'
#953000
1*
#954000
0*
1)
#955000
1*
#956000
0*
0)
1(
#957000
1*
#958000
0*
1)
#959000
1*
#960000
0*
0)
0(
0'
0&
0%
1$
14
#961000
1*
#962000
0*
1)
#963000
1*
#964000
0*
0)
1(
#965000
1*
#966000
0*
1)
#967000
1*
#968000
0*
0)
0(
1'
#969000
1*
#970000
0*
1)
#971000
1*
#972000
0*
0)
1(
#973000
1*
#974000
0*
1)
#975000
1*
#976000
0*
0)
0(
0'
1&
#977000
1*
#978000
0*
1)
#979000
1*
#980000
0*
0)
1(
#981000
1*
#982000
0*
1)
#983000
1*
#984000
0*
0)
0(
1'
#985000
1*
#986000
0*
1)
#987000
1*
#988000
0*
0)
1(
#989000
1*
#990000
0*
1)
#991000
1*
#992000
0*
0)
0(
0'
0&
1%
#993000
1*
#994000
0*
1)
#995000
1*
#996000
0*
0)
1(
#997000
1*
#998000
0*
1)
#999000
1*
#1000000
0*
0)
0(
1'
#1001000
1*
#1002000
0*
1)
#1003000
1*
#1004000
0*
0)
1(
#1005000
1*
#1006000
0*
1)
#1007000
1*
#1008000
0*
0)
0(
0'
1&
#1009000
1*
#1010000
0*
1)
#1011000
1*
#1012000
0*
0)
1(
#1013000
1*
#1014000
0*
1)
#1015000
1*
#1016000
0*
0)
0(
1'
#1017000
1*
#1018000
0*
1)
#1019000
1*
#1020000
0*
0)
1(
#1021000
1*
#1022000
0*
1)
#1023000
1*
