tarefa1/part2.vhd
library ieee;
use ieee.std_logic_1164.all;

-- Multiplexador 2:1 de 4 bits

entity part2 is
    port (
        SW   : in  std_logic_vector(9 downto 0);
        LEDG : out std_logic_vector(9 downto 0)
    );
end part2;

architecture rtl of part2 is
begin
    LEDG(3 downto 0) <= SW(3 downto 0) when SW(9) = '0' else SW(7 downto 4);
    LEDG(8 downto 4) <= (others => '0');
    LEDG(9)          <= SW(9);
end rtl;

tarefa1/part2_tb.vhd
library ieee;
use ieee.std_logic_1164.all;
use ieee.numeric_std.all;

entity part2_tb is
end part2_tb;

architecture test of part2_tb is
    signal SW   : std_logic_vector(9 downto 0) := (others => '0');
    signal LEDG : std_logic_vector(9 downto 0);
begin
    dut : entity work.part2(rtl)
        port map (
            SW   => SW,
            LEDG => LEDG
        );

    stimulus : process
        variable switches : std_logic_vector(9 downto 0);
    begin
        for selector in 0 to 1 loop
            for x in 0 to 15 loop
                for y in 0 to 15 loop
                    switches := (others => '0');
                    switches(9)          := '0';
                    switches(3 downto 0) := std_logic_vector(to_unsigned(x, 4));
                    switches(7 downto 4) := std_logic_vector(to_unsigned(y, 4));

                    if selector = 1 then
                        switches(9) := '1';
                    end if;

                    SW <= switches;
                    wait for 1 ns;

                    if selector = 0 then
                        assert LEDG(3 downto 0) = switches(3 downto 0)
                            report "MUX deveria selecionar X" severity error;
                    else
                        assert LEDG(3 downto 0) = switches(7 downto 4)
                            report "MUX deveria selecionar Y" severity error;
                    end if;

                    assert LEDG(9) = switches(9) and LEDG(8 downto 4) = "00000"
                        report "Indicadores LEDG incorretos" severity error;
                end loop;
            end loop;
        end loop;

        report "Parte 2: 512 casos aprovados" severity note;
        wait;
    end process;
end test;

tarefa1/part2.vcd
$date
	Mon Sep 14 18:02:06 2026
$end
$version
	ModelSim Version 10.1d
$end
$timescale
	1ps
$end
$scope module part2_tb $end
$var wire 1 ! SW [9] $end
$var wire 1 " SW [8] $end
$var wire 1 # SW [7] $end
$var wire 1 $ SW [6] $end
$var wire 1 % SW [5] $end
$var wire 1 & SW [4] $end
$var wire 1 ' SW [3] $end
$var wire 1 ( SW [2] $end
$var wire 1 ) SW [1] $end
$var wire 1 * SW [0] $end
$var wire 1 + LEDG [9] $end
$var wire 1 , LEDG [8] $end
$var wire 1 - LEDG [7] $end
$var wire 1 . LEDG [6] $end
$var wire 1 / LEDG [5] $end
$var wire 1 0 LEDG [4] $end
$var wire 1 1 LEDG [3] $end
$var wire 1 2 LEDG [2] $end
$var wire 1 3 LEDG [1] $end
$var wire 1 4 LEDG [0] $end
$scope module dut $end
$var wire 1 ! SW [9] $end
$var wire 1 " SW [8] $end
$var wire 1 # SW [7] $end
$var wire 1 $ SW [6] $end
$var wire 1 % SW [5] $end
$var wire 1 & SW [4] $end
$var wire 1 ' SW [3] $end
$var wire 1 ( SW [2] $end
$var wire 1 ) SW [1] $end
$var wire 1 * SW [0] $end
$var wire 1 + LEDG [9] $end
$var wire 1 , LEDG [8] $end
$var wire 1 - LEDG [7] $end
$var wire 1 . LEDG [6] $end
$var wire 1 / LEDG [5] $end
$var wire 1 0 LEDG [4] $end
$var wire 1 1 LEDG [3] $end
$var wire 1 2 LEDG [2] $end
$var wire 1 3 LEDG [1] $end
$var wire 1 4 LEDG [0] $end
$upscope $end
$upscope $end
$enddefinitions $end
#0
$dumpvars
0!
0"
0#
0$
0%
0&
0'
0(
0)
0*
0+
0,
0-
0.
0/
00
01
02
03
04
$end
#1000
1&
#2000
0&
1%
#3000
1&
#4000
0&
0%
1$
#5000
1&
#6000
0&
1%
#7000
1&
#8000
0&
0%
0$
1#
#9000
1&
#10000
0&
1%
#11000
1&
#12000
0&
0%
1$
#13000
1&
#14000
0&
1%
#15000
1&
#16000
1*
0&
0%
0$
0#
14
#17000
1&
#18000
0&
1%
#19000
1&
#20000
0&
0%
1$
#21000
1&
#22000
0&
1%
#23000
1&
#24000
0&
0%
0$
1#
#25000
1&
#26000
0&
1%
#27000
1&
#28000
0&
0%
1$
#29000
1&
#30000
0&
1%
#31000
1&
#32000
0*
1)
0&
0%
0$
0#
04
13
#33000
1&
#34000
0&
1%
#35000
1&
#36000
0&
0%
1$
#37000
1&
#38000
0&
1%
#39000
1&
#40000
0&
0%
0$
1#
#41000
1&
#42000
0&
1%
#43000
1&
#44000
0&
0%
1$
#45000
1&
#46000
0&
1%
#47000
1&
#48000
1*
0&
0%
0$
0#
14
#49000
1&
#50000
0&
1%
#51000
1&
#52000
0&
0%
1$
#53000
1&
#54000
0&
1%
#55000
1&
#56000
0&
0%
0$
1#
#57000
1&
#58000
0&
1%
#59000
1&
#60000
0&
0%
1$
#61000
1&
#62000
0&
1%
#63000
1&
#64000
0*
0)
1(
0&
0%
0$
0#
04
03
12
#65000
1&
#66000
0&
1%
#67000
1&
#68000
0&
0%
1$
#69000
1&
#70000
0&
1%
#71000
1&
#72000
0&
0%
0$
1#
#73000
1&
#74000
0&
1%
#75000
1&
#76000
0&
0%
1$
#77000
1&
#78000
0&
1%
#79000
1&
#80000
1*
0&
0%
0$
0#
14
#81000
1&
#82000
0&
1%
#83000
1&
#84000
0&
0%
1$
#85000
1&
#86000
0&
1%
#87000
1&
#88000
0&
0%
0$
1#
#89000
1&
#90000
0&
1%
#91000
1&
#92000
0&
0%
1$
#93000
1&
#94000
0&
1%
#95000
1&
#96000
0*
1)
0&
0%
0$
0#
04
13
#97000
1&
#98000
0&
1%
#99000
1&
#100000
0&
0%
1$
#101000
1&
#102000
0&
1%
#103000
1&
#104000
0&
0%
0$
1#
#105000
1&
#106000
0&
1%
#107000
1&
#108000
0&
0%
1$
#109000
1&
#110000
0&
1%
#111000
1&
#112000
1*
0&
0%
0$
0#
14
#113000
1&
#114000
0&
1%
#115000
1&
#116000
0&
0%
1$
#117000
1&
#118000
0&
1%
#119000
1&
#120000
0&
0%
0$
1#
#121000
1&
#122000
0&
1%
#123000
1&
#124000
0&
0%
1$
#125000
1&
#126000
0&
1%
#127000
1&
#128000
0*
0)
0(
1'
0&
0%
0$
0#
04
03
02
11
#129000
1&
#130000
0&
1%
#131000
1&
#132000
0&
0%
1$
#133000
1&
#134000
0&
1%
#135000
1&
#136000
0&
0%
0$
1#
#137000
1&
#138000
0&
1%
#139000
1&
#140000
0&
0%
1$
#141000
1&
#142000
0&
1%
#143000
1&
#144000
1*
0&
0%
0$
0#
14
#145000
1&
#146000
0&
1%
#147000
1&
#148000
0&
0%
1$
#149000
1&
#150000
0&
1%
#151000
1&
#152000
0&
0%
0$
1#
#153000
1&
#154000
0&
1%
#155000
1&
#156000
0&
0%
1$
#157000
1&
#158000
0&
1%
#159000
1&
#160000
0*
1)
0&
0%
0$
0#
04
13
#161000
1&
#162000
0&
1%
#163000
1&
#164000
0&
0%
1$
#165000
1&
#166000
0&
1%
#167000
1&
#168000
0&
0%
0$
1#
#169000
1&
#170000
0&
1%
#171000
1&
#172000
0&
0%
1$
#173000
1&
#174000
0&
1%
#175000
1&
#176000
1*
0&
0%
0$
0#
14
#177000
1&
#178000
0&
1%
#179000
1&
#180000
0&
0%
1$
#181000
1&
#182000
0&
1%
#183000
1&
#184000
0&
0%
0$
1#
#185000
1&
#186000
0&
1%
#187000
1&
#188000
0&
0%
1$
#189000
1&
#190000
0&
1%
#191000
1&
#192000
0*
0)
1(
0&
0%
0$
0#
04
03
12
#193000
1&
#194000
0&
1%
#195000
1&
#196000
0&
0%
1$
#197000
1&
#198000
0&
1%
#199000
1&
#200000
0&
0%
0$
1#
#201000
1&
#202000
0&
1%
#203000
1&
#204000
0&
0%
1$
#205000
1&
#206000
0&
1%
#207000
1&
#208000
1*
0&
0%
0$
0#
14
#209000
1&
#210000
0&
1%
#211000
1&
#212000
0&
0%
1$
#213000
1&
#214000
0&
1%
#215000
1&
#216000
0&
0%
0$
1#
#217000
1&
#218000
0&
1%
#219000
1&
#220000
0&
0%
1$
#221000
1&
#222000
0&
1%
#223000
1&
#224000
0*
1)
0&
0%
0$
0#
04
13
#225000
1&
#226000
0&
1%
#227000
1&
#228000
0&
0%
1$
#229000
1&
#230000
0&
1%
#231000
1&
#232000
0&
0%
0$
1#
#233000
1&
#234000
0&
1%
#235000
1&
#236000
0&
0%
1$
#237000
1&
#238000
0&
1%
#239000
1&
#240000
1*
0&
0%
0$
0#
14
#241000
1&
#242000
0&
1%
#243000
1&
#244000
0&
0%
1$
#245000
1&
#246000
0&
1%
#247000
1&
#248000
0&
0%
0$
1#
#249000
1&
#250000
0&
1%
#251000
1&
#252000
0&
0%
1$
#253000
1&
#254000
0&
1%
#255000
1&
#256000
0*
0)
0(
0'
0&
0%
0$
0#
1!
04
03
02
01
1+
#257000
1&
14
#258000
0&
1%
04
13
#259000
1&
14
#260000
0&
0%
1$
04
03
12
#261000
1&
14
#262000
0&
1%
04
13
#263000
1&
14
#264000
0&
0%
0$
1#
04
03
02
11
#265000
1&
14
#266000
0&
1%
04
13
#267000
1&
14
#268000
0&
0%
1$
04
03
12
#269000
1&
14
#270000
0&
1%
04
13
#271000
1&
14
#272000
1*
0&
0%
0$
0#
04
03
02
01
#273000
1&
14
#274000
0&
1%
04
13
#275000
1&
14
#276000
0&
0%
1$
04
03
12
#277000
1&
14
#278000
0&
1%
04
13
#279000
1&
14
#280000
0&
0%
0$
1#
04
03
02
11
#281000
1&
14
#282000
0&
1%
04
13
#283000
1&
14
#284000
0&
0%
1$
04
03
12
#285000
1&
14
#286000
0&
1%
04
13
#287000
1&
14
#288000
0*
1)
0&
0%
0$
0#
04
03
02
01
#289000
1&
14
#290000
0&
1%
04
13
#291000
1&
14
#292000
0&
0%
1$
04
03
12
#293000
1&
14
#294000
0&
1%
04
13
#295000
1&
14
#296000
0&
0%
0$
1#
04
03
02
11
#297000
1&
14
#298000
0&
1%
04
13
#299000
1&
14
#300000
0&
0%
1$
04
03
12
#301000
1&
14
#302000
0&
1%
04
13
#303000
1&
14
#304000
1*
0&
0%
0$
0#
04
03
02
01
#305000
1&
14
#306000
0&
1%
04
13
#307000
1&
14
#308000
0&
0%
1$
04
03
12
#309000
1&
14
#310000
0&
1%
04
13
#311000
1&
14
#312000
0&
0%
0$
1#
04
03
02
11
#313000
1&
14
#314000
0&
1%
04
13
#315000
1&
14
#316000
0&
0%
1$
04
03
12
#317000
1&
14
#318000
0&
1%
04
13
#319000
1&
14
#320000
0*
0)
1(
0&
0%
0$
0#
04
03
02
01
#321000
1&
14
#322000
0&
1%
04
13
#323000
1&
14
#324000
0&
0%
1$
04
03
12
#325000
1&
14
#326000
0&
1%
04
13
#327000
1&
14
#328000
0&
0%
0$
1#
04
03
02
11
#329000
1&
14
#330000
0&
1%
04
13
#331000
1&
14
#332000
0&
0%
1$
04
03
12
#333000
1&
14
#334000
0&
1%
04
13
#335000
1&
14
#336000
1*
0&
0%
0$
0#
04
03
02
01
#337000
1&
14
#338000
0&
1%
04
13
#339000
1&
14
#340000
0&
0%
1$
04
03
12
#341000
1&
14
#342000
0&
1%
04
13
#343000
1&
14
#344000
0&
0%
0$
1#
04
03
02
11
#345000
1&
14
#346000
0&
1%
04
13
#347000
1&
14
#348000
0&
0%
1$
04
03
12
#349000
1&
14
#350000
0&
1%
04
13
#351000
1&
14
#352000
0*
1)
0&
0%
0$
0#
04
03
02
01
#353000
1&
14
#354000
0&
1%
04
13
#355000
1&
14
#356000
0&
0%
1$
04
03
12
#357000
1&
14
#358000
0&
1%
04
13
#359000
1&
14
#360000
0&
0%
0$
1#
04
03
02
11
#361000
1&
14
#362000
0&
1%
04
13
#363000
1&
14
#364000
0&
0%
1$
04
03
12
#365000
1&
14
#366000
0&
1%
04
13
#367000
1&
14
#368000
1*
0&
0%
0$
0#
04
03
02
01
#369000
1&
14
#370000
0&
1%
04
13
#371000
1&
14
#372000
0&
0%
1$
04
03
12
#373000
1&
14
#374000
0&
1%
04
13
#375000
1&
14
#376000
0&
0%
0$
1#
04
03
02
11
#377000
1&
14
#378000
0&
1%
04
13
#379000
1&
14
#380000
0&
0%
1$
04
03
12
#381000
1&
14
#382000
0&
1%
04
13
#383000
1&
14
#384000
0*
0)
0(
1'
0&
0%
0$
0#
04
03
02
01
#385000
1&
14
#386000
0&
1%
04
13
#387000
1&
14
#388000
0&
0%
1$
04
03
12
#389000
1&
14
#390000
0&
1%
04
13
#391000
1&
14
#392000
0&
0%
0$
1#
04
03
02
11
#393000
1&
14
#394000
0&
1%
04
13
#395000
1&
14
#396000
0&
0%
1$
04
03
12
#397000
1&
14
#398000
0&
1%
04
13
#399000
1&
14
#400000
1*
0&
0%
0$
0#
04
03
02
01
#401000
1&
14
#402000
0&
1%
04
13
#403000
1&
14
#404000
0&
0%
1$
04
03
12
#405000
1&
14
#406000
0&
1%
04
13
#407000
1&
14
#408000
0&
0%
0$
1#
04
03
02
11
#409000
1&
14
#410000
0&
1%
04
13
#411000
1&
14
#412000
0&
0%
1$
04
03
12
#413000
1&
14
#414000
0&
1%
04
13
#415000
1&
14
#416000
0*
1)
0&
0%
0$
0#
04
03
02
01
#417000
1&
14
#418000
0&
1%
04
13
#419000
1&
14
#420000
0&
0%
1$
04
03
12
#421000
1&
14
#422000
0&
1%
04
13
#423000
1&
14
#424000
0&
0%
0$
1#
04
03
02
11
#425000
1&
14
#426000
0&
1%
04
13
#427000
1&
14
#428000
0&
0%
1$
04
03
12
#429000
1&
14
#430000
0&
1%
04
13
#431000
1&
14
#432000
1*
0&
0%
0$
0#
04
03
02
01
#433000
1&
14
#434000
0&
1%
04
13
#435000
1&
14
#436000
0&
0%
1$
04
03
12
#437000
1&
14
#438000
0&
1%
04
13
#439000
1&
14
#440000
0&
0%
0$
1#
04
03
02
11
#441000
1&
14
#442000
0&
1%
04
13
#443000
1&
14
#444000
0&
0%
1$
04
03
12
#445000
1&
14
#446000
0&
1%
04
13
#447000
1&
14
#448000
0*
0)
1(
0&
0%
0$
0#
04
03
02
01
#449000
1&
14
#450000
0&
1%
04
13
#451000
1&
14
#452000
0&
0%
1$
04
03
12
#453000
1&
14
#454000
0&
1%
04
13
#455000
1&
14
#456000
0&
0%
0$
1#
04
03
02
11
#457000
1&
14
#458000
0&
1%
04
13
#459000
1&
14
#460000
0&
0%
1$
04
03
12
#461000
1&
14
#462000
0&
1%
04
13
#463000
1&
14
#464000
1*
0&
0%
0$
0#
04
03
02
01
#465000
1&
14
#466000
0&
1%
04
13
#467000
1&
14
#468000
0&
0%
1$
04
03
12
#469000
1&
14
#470000
0&
1%
04
13
#471000
1&
14
#472000
0&
0%
0$
1#
04
03
02
11
#473000
1&
14
#474000
0&
1%
04
13
#475000
1&
14
#476000
0&
0%
1$
04
03
12
#477000
1&
14
#478000
0&
1%
04
13
#479000
1&
14
#480000
0*
1)
0&
0%
0$
0#
04
03
02
01
#481000
1&
14
#482000
0&
1%
04
13
#483000
1&
14
#484000
0&
0%
1$
04
03
12
#485000
1&
14
#486000
0&
1%
04
13
#487000
1&
14
#488000
0&
0%
0$
1#
04
03
02
11
#489000
1&
14
#490000
0&
1%
04
13
#491000
1&
14
#492000
0&
0%
1$
04
03
12
#493000
1&
14
#494000
0&
1%
04
13
#495000
1&
14
#496000
1*
0&
0%
0$
0#
04
03
02
01
#497000
1&
14
#498000
0&
1%
04
13
#499000
1&
14
#500000
0&
0%
1$
04
03
12
#501000
1&
14
#502000
0&
1%
04
13
#503000
1&
14
#504000
0&
0%
0$
1#
04
03
02
11
#505000
1&
14
#506000
0&
1%
04
13
#507000
1&
14
#508000
0&
0%
1$
04
03
12
#509000
1&
14
#510000
0&
1%
04
13
#511000
1&
14
