tarefa1/part1.vhd
LIBRARY ieee;
USE ieee.std_logic_1164.all;

-- chaves e leds

ENTITY part1 IS
PORT (SW : IN STD_LOGIC_VECTOR(9 DOWNTO 0);
		LEDG : OUT STD_LOGIC_VECTOR(9 DOWNTO 0));
END part1;

-- atribuicao corrente direta

ARCHITECTURE hardware OF part1 IS
BEGIN LEDG <= SW;
END hardware;

tarefa1/part1.vcd
$date
	Wed Sep  9 19:37:13 2026
$end
$version
	ModelSim Version 10.1d
$end
$timescale
	1ps
$end
$scope module part1 $end
$var wire 1 ! SW [9] $end
$var wire 1 " SW [8] $end
$var wire 1 # SW [7] $end
$var wire 1 $ SW [6] $end
$var wire 1 % SW [5] $end
$var wire 1 & SW [4] $end
$var wire 1 ' SW [3] $end
$var wire 1 ( SW [2] $end
$var wire 1 ) SW [1] $end
$var wire 1 * SW [0] $end
$var wire 1 + LEDG [9] $end
$var wire 1 , LEDG [8] $end
$var wire 1 - LEDG [7] $end
$var wire 1 . LEDG [6] $end
$var wire 1 / LEDG [5] $end
$var wire 1 0 LEDG [4] $end
$var wire 1 1 LEDG [3] $end
$var wire 1 2 LEDG [2] $end
$var wire 1 3 LEDG [1] $end
$var wire 1 4 LEDG [0] $end
$upscope $end
$enddefinitions $end
#0
$dumpvars
0+
0,
0-
0.
0/
00
01
02
03
04
0!
0"
0#
0$
0%
0&
0'
0(
0)
0*
$end
#50000
1*
14
#100000
1)
0*
04
13
#150000
1*
14
#200000
1(
0)
0*
04
03
12
#250000
1*
14
#300000
1)
0*
04
13
#350000
1*
14
#400000
1'
0(
0)
0*
04
03
02
11
#450000
1*
14
#500000
1)
0*
04
13
#550000
1*
14
#600000
1(
0)
0*
04
03
12
#650000
1*
14
#700000
1)
0*
04
13
#750000
1*
14
#800000
1&
0'
0(
0)
0*
04
03
02
01
10
#850000
1*
14
#900000
1)
0*
04
13
#950000
1*
14
#1000000
1(
0)
0*
04
03
12
#1050000
1*
14
#1100000
1)
0*
04
13
#1150000
1*
14
#1200000
1'
0(
0)
0*
04
03
02
11
#1250000
1*
14
#1300000
1)
0*
04
13
#1350000
1*
14
#1400000
1(
0)
0*
04
03
12
#1450000
1*
14
#1500000
1)
0*
04
13
#1550000
1*
14
#1600000
1%
0&
0'
0(
0)
0*
04
03
02
01
00
1/
#1650000
1*
14
#1700000
1)
0*
04
13
#1750000
1*
14
#1800000
1(
0)
0*
04
03
12
#1850000
1*
14
#1900000
1)
0*
04
13
#1950000
1*
14
#2000000
1'
0(
0)
0*
04
03
02
11
#2050000
1*
14
#2100000
1)
0*
04
13
#2150000
1*
14
#2200000
1(
0)
0*
04
03
12
#2250000
1*
14
#2300000
1)
0*
04
13
#2350000
1*
14
#2400000
1&
0'
0(
0)
0*
04
03
02
01
10
#2450000
1*
14
#2500000
1)
0*
04
13
#2550000
1*
14
#2600000
1(
0)
0*
04
03
12
#2650000
1*
14
#2700000
1)
0*
04
13
#2750000
1*
14
#2800000
1'
0(
0)
0*
04
03
02
11
#2850000
1*
14
#2900000
1)
0*
04
13
#2950000
1*
14
#3000000
1(
0)
0*
04
03
12
#3050000
1*
14
#3100000
1)
0*
04
13
#3150000
1*
14
#3200000
1$
0%
0&
0'
0(
0)
0*
04
03
02
01
00
0/
1.
#3250000
1*
14
#3300000
1)
0*
04
13
#3350000
1*
14
#3400000
1(
0)
0*
04
03
12
#3450000
1*
14
#3500000
1)
0*
04
13
#3550000
1*
14
#3600000
1'
0(
0)
0*
04
03
02
11
#3650000
1*
14
#3700000
1)
0*
04
13
#3750000
1*
14
#3800000
1(
0)
0*
04
03
12
#3850000
1*
14
#3900000
1)
0*
04
13
#3950000
1*
14
#4000000
1&
0'
0(
0)
0*
04
03
02
01
10
#4050000
1*
14
#4100000
1)
0*
04
13
#4150000
1*
14
#4200000
1(
0)
0*
04
03
12
#4250000
1*
14
#4300000
1)
0*
04
13
#4350000
1*
14
#4400000
1'
0(
0)
0*
04
03
02
11
#4450000
1*
14
#4500000
1)
0*
04
13
#4550000
1*
14
#4600000
1(
0)
0*
04
03
12
#4650000
1*
14
#4700000
1)
0*
04
13
#4750000
1*
14
#4800000
1%
0&
0'
0(
0)
0*
04
03
02
01
00
1/
#4850000
1*
14
#4900000
1)
0*
04
13
#4950000
1*
14
#5000000
1(
0)
0*
04
03
12
#5050000
1*
14
#5100000
1)
0*
04
13
#5150000
1*
14
#5200000
1'
0(
0)
0*
04
03
02
11
#5250000
1*
14
#5300000
1)
0*
04
13
#5350000
1*
14
#5400000
1(
0)
0*
04
03
12
#5450000
1*
14
#5500000
1)
0*
04
13
#5550000
1*
14
#5600000
1&
0'
0(
0)
0*
04
03
02
01
10
#5650000
1*
14
#5700000
1)
0*
04
13
#5750000
1*
14
#5800000
1(
0)
0*
04
03
12
#5850000
1*
14
#5900000
1)
0*
04
13
#5950000
1*
14
#6000000
1'
0(
0)
0*
04
03
02
11
#6050000
1*
14
#6100000
1)
0*
04
13
#6150000
1*
14
#6200000
1(
0)
0*
04
03
12
#6250000
1*
14
#6300000
1)
0*
04
13
#6350000
1*
14
#6400000
1#
0$
0%
0&
0'
0(
0)
0*
04
03
02
01
00
0/
0.
1-
#6450000
1*
14
#6500000
1)
0*
04
13
#6550000
1*
14
#6600000
1(
0)
0*
04
03
12
#6650000
1*
14
#6700000
1)
0*
04
13
#6750000
1*
14
#6800000
1'
0(
0)
0*
04
03
02
11
#6850000
1*
14
#6900000
1)
0*
04
13
#6950000
1*
14
#7000000
1(
0)
0*
04
03
12
#7050000
1*
14
#7100000
1)
0*
04
13
#7150000
1*
14
#7200000
1&
0'
0(
0)
0*
04
03
02
01
10
#7250000
1*
14
#7300000
1)
0*
04
13
#7350000
1*
14
#7400000
1(
0)
0*
04
03
12
#7450000
1*
14
#7500000
1)
0*
04
13
#7550000
1*
14
#7600000
1'
0(
0)
0*
04
03
02
11
#7650000
1*
14
#7700000
1)
0*
04
13
#7750000
1*
14
#7800000
1(
0)
0*
04
03
12
#7850000
1*
14
#7900000
1)
0*
04
13
#7950000
1*
14
#8000000
1%
0&
0'
0(
0)
0*
04
03
02
01
00
1/
#8050000
1*
14
#8100000
1)
0*
04
13
#8150000
1*
14
#8200000
1(
0)
0*
04
03
12
#8250000
1*
14
#8300000
1)
0*
04
13
#8350000
1*
14
#8400000
1'
0(
0)
0*
04
03
02
11
#8450000
1*
14
#8500000
1)
0*
04
13
#8550000
1*
14
#8600000
1(
0)
0*
04
03
12
#8650000
1*
14
#8700000
1)
0*
04
13
#8750000
1*
14
#8800000
1&
0'
0(
0)
0*
04
03
02
01
10
#8850000
1*
14
#8900000
1)
0*
04
13
#8950000
1*
14
#9000000
1(
0)
0*
04
03
12
#9050000
1*
14
#9100000
1)
0*
04
13
#9150000
1*
14
#9200000
1'
0(
0)
0*
04
03
02
11
#9250000
1*
14
#9300000
1)
0*
04
13
#9350000
1*
14
#9400000
1(
0)
0*
04
03
12
#9450000
1*
14
#9500000
1)
0*
04
13
#9550000
1*
14
#9600000
1$
0%
0&
0'
0(
0)
0*
04
03
02
01
00
0/
1.
#9650000
1*
14
#9700000
1)
0*
04
13
#9750000
1*
14
#9800000
1(
0)
0*
04
03
12
#9850000
1*
14
#9900000
1)
0*
04
13
#9950000
1*
14
#10000000
1'
0(
0)
0*
04
03
02
11
#10050000
1*
14
#10100000
1)
0*
04
13
#10150000
1*
14
#10200000
1(
0)
0*
04
03
12
#10250000
1*
14
#10300000
1)
0*
04
13
#10350000
1*
14
#10400000
1&
0'
0(
0)
0*
04
03
02
01
10
#10450000
1*
14
#10500000
1)
0*
04
13
#10550000
1*
14
#10600000
1(
0)
0*
04
03
12
#10650000
1*
14
#10700000
1)
0*
04
13
#10750000
1*
14
#10800000
1'
0(
0)
0*
04
03
02
11
#10850000
1*
14
#10900000
1)
0*
04
13
#10950000
1*
14
#11000000
1(
0)
0*
04
03
12
#11050000
1*
14
#11100000
1)
0*
04
13
#11150000
1*
14
#11200000
1%
0&
0'
0(
0)
0*
04
03
02
01
00
1/
#11250000
1*
14
#11300000
1)
0*
04
13
#11350000
1*
14
#11400000
1(
0)
0*
04
03
12
#11450000
1*
14
#11500000
1)
0*
04
13
#11550000
1*
14
#11600000
1'
0(
0)
0*
04
03
02
11
#11650000
1*
14
#11700000
1)
0*
04
13
#11750000
1*
14
#11800000
1(
0)
0*
04
03
12
#11850000
1*
14
#11900000
1)
0*
04
13
#11950000
1*
14
#12000000
1&
0'
0(
0)
0*
04
03
02
01
10
#12050000
1*
14
#12100000
1)
0*
04
13
#12150000
1*
14
#12200000
1(
0)
0*
04
03
12
#12250000
1*
14
#12300000
1)
0*
04
13
#12350000
1*
14
#12400000
1'
0(
0)
0*
04
03
02
11
#12450000
1*
14
#12500000
1)
0*
04
13
#12550000
1*
14
#12600000
1(
0)
0*
04
03
12
#12650000
1*
14
#12700000
1)
0*
04
13
#12750000
1*
14
#12800000
1"
0#
0$
0%
0&
0'
0(
0)
0*
04
03
02
01
00
0/
0.
0-
1,
#12850000
1*
14
#12900000
1)
0*
04
13
#12950000
1*
14
#13000000
1(
0)
0*
04
03
12
#13050000
1*
14
#13100000
1)
0*
04
13
#13150000
1*
14
#13200000
1'
0(
0)
0*
04
03
02
11
#13250000
1*
14
#13300000
1)
0*
04
13
#13350000
1*
14
#13400000
1(
0)
0*
04
03
12
#13450000
1*
14
#13500000
1)
0*
04
13
#13550000
1*
14
#13600000
1&
0'
0(
0)
0*
04
03
02
01
10
#13650000
1*
14
#13700000
1)
0*
04
13
#13750000
1*
14
#13800000
1(
0)
0*
04
03
12
#13850000
1*
14
#13900000
1)
0*
04
13
#13950000
1*
14
#14000000
1'
0(
0)
0*
04
03
02
11
#14050000
1*
14
#14100000
1)
0*
04
13
#14150000
1*
14
#14200000
1(
0)
0*
04
03
12
#14250000
1*
14
#14300000
1)
0*
04
13
#14350000
1*
14
#14400000
1%
0&
0'
0(
0)
0*
04
03
02
01
00
1/
#14450000
1*
14
#14500000
1)
0*
04
13
#14550000
1*
14
#14600000
1(
0)
0*
04
03
12
#14650000
1*
14
#14700000
1)
0*
04
13
#14750000
1*
14
#14800000
1'
0(
0)
0*
04
03
02
11
#14850000
1*
14
#14900000
1)
0*
04
13
#14950000
1*
14
#15000000
1(
0)
0*
04
03
12
#15050000
1*
14
#15100000
1)
0*
04
13
#15150000
1*
14
#15200000
1&
0'
0(
0)
0*
04
03
02
01
10
#15250000
1*
14
#15300000
1)
0*
04
13
#15350000
1*
14
#15400000
1(
0)
0*
04
03
12
#15450000
1*
14
#15500000
1)
0*
04
13
#15550000
1*
14
#15600000
1'
0(
0)
0*
04
03
02
11
#15650000
1*
14
#15700000
1)
0*
04
13
#15750000
1*
14
#15800000
1(
0)
0*
04
03
12
#15850000
1*
14
#15900000
1)
0*
04
13
#15950000
1*
14
#16000000
1$
0%
0&
0'
0(
0)
0*
04
03
02
01
00
0/
1.
#16050000
1*
14
#16100000
1)
0*
04
13
#16150000
1*
14
#16200000
1(
0)
0*
04
03
12
#16250000
1*
14
#16300000
1)
0*
04
13
#16350000
1*
14
#16400000
1'
0(
0)
0*
04
03
02
11
#16450000
1*
14
#16500000
1)
0*
04
13
#16550000
1*
14
#16600000
1(
0)
0*
04
03
12
#16650000
1*
14
#16700000
1)
0*
04
13
#16750000
1*
14
#16800000
1&
0'
0(
0)
0*
04
03
02
01
10
#16850000
1*
14
#16900000
1)
0*
04
13
#16950000
1*
14
#17000000
1(
0)
0*
04
03
12
#17050000
1*
14
#17100000
1)
0*
04
13
#17150000
1*
14
#17200000
1'
0(
0)
0*
04
03
02
11
#17250000
1*
14
#17300000
1)
0*
04
13
#17350000
1*
14
#17400000
1(
0)
0*
04
03
12
#17450000
1*
14
#17500000
1)
0*
04
13
#17550000
1*
14
#17600000
1%
0&
0'
0(
0)
0*
04
03
02
01
00
1/
#17650000
1*
14
#17700000
1)
0*
04
13
#17750000
1*
14
#17800000
1(
0)
0*
04
03
12
#17850000
1*
14
#17900000
1)
0*
04
13
#17950000
1*
14
#18000000
1'
0(
0)
0*
04
03
02
11
#18050000
1*
14
#18100000
1)
0*
04
13
#18150000
1*
14
#18200000
1(
0)
0*
04
03
12
#18250000
1*
14
#18300000
1)
0*
04
13
#18350000
1*
14
#18400000
1&
0'
0(
0)
0*
04
03
02
01
10
#18450000
1*
14
#18500000
1)
0*
04
13
#18550000
1*
14
#18600000
1(
0)
0*
04
03
12
#18650000
1*
14
#18700000
1)
0*
04
13
#18750000
1*
14
#18800000
1'
0(
0)
0*
04
03
02
11
#18850000
1*
14
#18900000
1)
0*
04
13
#18950000
1*
14
#19000000
1(
0)
0*
04
03
12
#19050000
1*
14
#19100000
1)
0*
04
13
#19150000
1*
14
#19200000
1#
0$
0%
0&
0'
0(
0)
0*
04
03
02
01
00
0/
0.
1-
#19250000
1*
14
#19300000
1)
0*
04
13
#19350000
1*
14
#19400000
1(
0)
0*
04
03
12
#19450000
1*
14
#19500000
1)
0*
04
13
#19550000
1*
14
#19600000
1'
0(
0)
0*
04
03
02
11
#19650000
1*
14
#19700000
1)
0*
04
13
#19750000
1*
14
#19800000
1(
0)
0*
04
03
12
#19850000
1*
14
#19900000
1)
0*
04
13
#19950000
1*
14
#20000000
1&
0'
0(
0)
0*
04
03
02
01
10
#20050000
1*
14
#20100000
1)
0*
04
13
#20150000
1*
14
#20200000
1(
0)
0*
04
03
12
#20250000
1*
14
#20300000
1)
0*
04
13
#20350000
1*
14
#20400000
1'
0(
0)
0*
04
03
02
11
#20450000
1*
14
#20500000
1)
0*
04
13
#20550000
1*
14
#20600000
1(
0)
0*
04
03
12
#20650000
1*
14
#20700000
1)
0*
04
13
#20750000
1*
14
#20800000
1%
0&
0'
0(
0)
0*
04
03
02
01
00
1/
#20850000
1*
14
#20900000
1)
0*
04
13
#20950000
1*
14
#21000000
1(
0)
0*
04
03
12
#21050000
1*
14
#21100000
1)
0*
04
13
#21150000
1*
14
#21200000
1'
0(
0)
0*
04
03
02
11
#21250000
1*
14
#21300000
1)
0*
04
13
#21350000
1*
14
#21400000
1(
0)
0*
04
03
12
#21450000
1*
14
#21500000
1)
0*
04
13
#21550000
1*
14
#21600000
1&
0'
0(
0)
0*
04
03
02
01
10
#21650000
1*
14
#21700000
1)
0*
04
13
#21750000
1*
14
#21800000
1(
0)
0*
04
03
12
#21850000
1*
14
#21900000
1)
0*
04
13
#21950000
1*
14
#22000000
1'
0(
0)
0*
04
03
02
11
#22050000
1*
14
#22100000
1)
0*
04
13
#22150000
1*
14
#22200000
1(
0)
0*
04
03
12
#22250000
1*
14
#22300000
1)
0*
04
13
#22350000
1*
14
#22400000
1$
0%
0&
0'
0(
0)
0*
04
03
02
01
00
0/
1.
#22450000
1*
14
#22500000
1)
0*
04
13
#22550000
1*
14
#22600000
1(
0)
0*
04
03
12
#22650000
1*
14
#22700000
1)
0*
04
13
#22750000
1*
14
#22800000
1'
0(
0)
0*
04
03
02
11
#22850000
1*
14
#22900000
1)
0*
04
13
#22950000
1*
14
#23000000
1(
0)
0*
04
03
12
#23050000
1*
14
#23100000
1)
0*
04
13
#23150000
1*
14
#23200000
1&
0'
0(
0)
0*
04
03
02
01
10
#23250000
1*
14
#23300000
1)
0*
04
13
#23350000
1*
14
#23400000
1(
0)
0*
04
03
12
#23450000
1*
14
#23500000
1)
0*
04
13
#23550000
1*
14
#23600000
1'
0(
0)
0*
04
03
02
11
#23650000
1*
14
#23700000
1)
0*
04
13
#23750000
1*
14
#23800000
1(
0)
0*
04
03
12
#23850000
1*
14
#23900000
1)
0*
04
13
#23950000
1*
14
#24000000
1%
0&
0'
0(
0)
0*
04
03
02
01
00
1/
#24050000
1*
14
#24100000
1)
0*
04
13
#24150000
1*
14
#24200000
1(
0)
0*
04
03
12
#24250000
1*
14
#24300000
1)
0*
04
13
#24350000
1*
14
#24400000
1'
0(
0)
0*
04
03
02
11
#24450000
1*
14
#24500000
1)
0*
04
13
#24550000
1*
14
#24600000
1(
0)
0*
04
03
12
#24650000
1*
14
#24700000
1)
0*
04
13
#24750000
1*
14
#24800000
1&
0'
0(
0)
0*
04
03
02
01
10
#24850000
1*
14
#24900000
1)
0*
04
13
#24950000
1*
14
#25000000
1(
0)
0*
04
03
12
#25050000
1*
14
#25100000
1)
0*
04
13
#25150000
1*
14
#25200000
1'
0(
0)
0*
04
03
02
11
#25250000
1*
14
#25300000
1)
0*
04
13
#25350000
1*
14
#25400000
1(
0)
0*
04
03
12
#25450000
1*
14
#25500000
1)
0*
04
13
#25550000
1*
14
#25600000
1!
0"
0#
0$
0%
0&
0'
0(
0)
0*
04
03
02
01
00
0/
0.
0-
0,
1+
#25650000
1*
14
#25700000
1)
0*
04
13
#25750000
1*
14
#25800000
1(
0)
0*
04
03
12
#25850000
1*
14
#25900000
1)
0*
04
13
#25950000
1*
14
#26000000
1'
0(
0)
0*
04
03
02
11
#26050000
1*
14
#26100000
1)
0*
04
13
#26150000
1*
14
#26200000
1(
0)
0*
04
03
12
#26250000
1*
14
#26300000
1)
0*
04
13
#26350000
1*
14
#26400000
1&
0'
0(
0)
0*
04
03
02
01
10
#26450000
1*
14
#26500000
1)
0*
04
13
#26550000
1*
14
#26600000
1(
0)
0*
04
03
12
#26650000
1*
14
#26700000
1)
0*
04
13
#26750000
1*
14
#26800000
1'
0(
0)
0*
04
03
02
11
#26850000
1*
14
#26900000
1)
0*
04
13
#26950000
1*
14
#27000000
1(
0)
0*
04
03
12
#27050000
1*
14
#27100000
1)
0*
04
13
#27150000
1*
14
#27200000
1%
0&
0'
0(
0)
0*
04
03
02
01
00
1/
#27250000
1*
14
#27300000
1)
0*
04
13
#27350000
1*
14
#27400000
1(
0)
0*
04
03
12
#27450000
1*
14
#27500000
1)
0*
04
13
#27550000
1*
14
#27600000
1'
0(
0)
0*
04
03
02
11
#27650000
1*
14
#27700000
1)
0*
04
13
#27750000
1*
14
#27800000
1(
0)
0*
04
03
12
#27850000
1*
14
#27900000
1)
0*
04
13
#27950000
1*
14
#28000000
1&
0'
0(
0)
0*
04
03
02
01
10
#28050000
1*
14
#28100000
1)
0*
04
13
#28150000
1*
14
#28200000
1(
0)
0*
04
03
12
#28250000
1*
14
#28300000
1)
0*
04
13
#28350000
1*
14
#28400000
1'
0(
0)
0*
04
03
02
11
#28450000
1*
14
#28500000
1)
0*
04
13
#28550000
1*
14
#28600000
1(
0)
0*
04
03
12
#28650000
1*
14
#28700000
1)
0*
04
13
#28750000
1*
14
#28800000
1$
0%
0&
0'
0(
0)
0*
04
03
02
01
00
0/
1.
#28850000
1*
14
#28900000
1)
0*
04
13
#28950000
1*
14
#29000000
1(
0)
0*
04
03
12
#29050000
1*
14
#29100000
1)
0*
04
13
#29150000
1*
14
#29200000
1'
0(
0)
0*
04
03
02
11
#29250000
1*
14
#29300000
1)
0*
04
13
#29350000
1*
14
#29400000
1(
0)
0*
04
03
12
#29450000
1*
14
#29500000
1)
0*
04
13
#29550000
1*
14
#29600000
1&
0'
0(
0)
0*
04
03
02
01
10
#29650000
1*
14
#29700000
1)
0*
04
13
#29750000
1*
14
#29800000
1(
0)
0*
04
03
12
#29850000
1*
14
#29900000
1)
0*
04
13
#29950000
1*
14
#30000000
1'
0(
0)
0*
04
03
02
11
#30050000
1*
14
#30100000
1)
0*
04
13
#30150000
1*
14
#30200000
1(
0)
0*
04
03
12
#30250000
1*
14
#30300000
1)
0*
04
13
#30350000
1*
14
#30400000
1%
0&
0'
0(
0)
0*
04
03
02
01
00
1/
#30450000
1*
14
#30500000
1)
0*
04
13
#30550000
1*
14
#30600000
1(
0)
0*
04
03
12
#30650000
1*
14
#30700000
1)
0*
04
13
#30750000
1*
14
#30800000
1'
0(
0)
0*
04
03
02
11
#30850000
1*
14
#30900000
1)
0*
04
13
#30950000
1*
14
#31000000
1(
0)
0*
04
03
12
#31050000
1*
14
#31100000
1)
0*
04
13
#31150000
1*
14
#31200000
1&
0'
0(
0)
0*
04
03
02
01
10
#31250000
1*
14
#31300000
1)
0*
04
13
#31350000
1*
14
#31400000
1(
0)
0*
04
03
12
#31450000
1*
14
#31500000
1)
0*
04
13
#31550000
1*
14
#31600000
1'
0(
0)
0*
04
03
02
11
#31650000
1*
14
#31700000
1)
0*
04
13
#31750000
1*
14
#31800000
1(
0)
0*
04
03
12
#31850000
1*
14
#31900000
1)
0*
04
13
#31950000
1*
14
#32000000
1#
0$
0%
0&
0'
0(
0)
0*
04
03
02
01
00
0/
0.
1-
#32050000
1*
14
#32100000
1)
0*
04
13
#32150000
1*
14
#32200000
1(
0)
0*
04
03
12
#32250000
1*
14
#32300000
1)
0*
04
13
#32350000
1*
14
#32400000
1'
0(
0)
0*
04
03
02
11
#32450000
1*
14
#32500000
1)
0*
04
13
#32550000
1*
14
#32600000
1(
0)
0*
04
03
12
#32650000
1*
14
#32700000
1)
0*
04
13
#32750000
1*
14
#32800000
1&
0'
0(
0)
0*
04
03
02
01
10
#32850000
1*
14
#32900000
1)
0*
04
13
#32950000
1*
14
#33000000
1(
0)
0*
04
03
12
#33050000
1*
14
#33100000
1)
0*
04
13
#33150000
1*
14
#33200000
1'
0(
0)
0*
04
03
02
11
#33250000
1*
14
#33300000
1)
0*
04
13
#33350000
1*
14
#33400000
1(
0)
0*
04
03
12
#33450000
1*
14
#33500000
1)
0*
04
13
#33550000
1*
14
#33600000
1%
0&
0'
0(
0)
0*
04
03
02
01
00
1/
#33650000
1*
14
#33700000
1)
0*
04
13
#33750000
1*
14
#33800000
1(
0)
0*
04
03
12
#33850000
1*
14
#33900000
1)
0*
04
13
#33950000
1*
14
#34000000
1'
0(
0)
0*
04
03
02
11
#34050000
1*
14
#34100000
1)
0*
04
13
#34150000
1*
14
#34200000
1(
0)
0*
04
03
12
#34250000
1*
14
#34300000
1)
0*
04
13
#34350000
1*
14
#34400000
1&
0'
0(
0)
0*
04
03
02
01
10
#34450000
1*
14
#34500000
1)
0*
04
13
#34550000
1*
14
#34600000
1(
0)
0*
04
03
12
#34650000
1*
14
#34700000
1)
0*
04
13
#34750000
1*
14
#34800000
1'
0(
0)
0*
04
03
02
11
#34850000
1*
14
#34900000
1)
0*
04
13
#34950000
1*
14
#35000000
1(
0)
0*
04
03
12
#35050000
1*
14
#35100000
1)
0*
04
13
#35150000
1*
14
#35200000
1$
0%
0&
0'
0(
0)
0*
04
03
02
01
00
0/
1.
#35250000
1*
14
#35300000
1)
0*
04
13
#35350000
1*
14
#35400000
1(
0)
0*
04
03
12
#35450000
1*
14
#35500000
1)
0*
04
13
#35550000
1*
14
#35600000
1'
0(
0)
0*
04
03
02
11
#35650000
1*
14
#35700000
1)
0*
04
13
#35750000
1*
14
#35800000
1(
0)
0*
04
03
12
#35850000
1*
14
#35900000
1)
0*
04
13
#35950000
1*
14
#36000000
1&
0'
0(
0)
0*
04
03
02
01
10
#36050000
1*
14
#36100000
1)
0*
04
13
#36150000
1*
14
#36200000
1(
0)
0*
04
03
12
#36250000
1*
14
#36300000
1)
0*
04
13
#36350000
1*
14
#36400000
1'
0(
0)
0*
04
03
02
11
#36450000
1*
14
#36500000
1)
0*
04
13
#36550000
1*
14
#36600000
1(
0)
0*
04
03
12
#36650000
1*
14
#36700000
1)
0*
04
13
#36750000
1*
14
#36800000
1%
0&
0'
0(
0)
0*
04
03
02
01
00
1/
#36850000
1*
14
#36900000
1)
0*
04
13
#36950000
1*
14
#37000000
1(
0)
0*
04
03
12
#37050000
1*
14
#37100000
1)
0*
04
13
#37150000
1*
14
#37200000
1'
0(
0)
0*
04
03
02
11
#37250000
1*
14
#37300000
1)
0*
04
13
#37350000
1*
14
#37400000
1(
0)
0*
04
03
12
#37450000
1*
14
#37500000
1)
0*
04
13
#37550000
1*
14
#37600000
1&
0'
0(
0)
0*
04
03
02
01
10
#37650000
1*
14
#37700000
1)
0*
04
13
#37750000
1*
14
#37800000
1(
0)
0*
04
03
12
#37850000
1*
14
#37900000
1)
0*
04
13
#37950000
1*
14
#38000000
1'
0(
0)
0*
04
03
02
11
#38050000
1*
14
#38100000
1)
0*
04
13
#38150000
1*
14
#38200000
1(
0)
0*
04
03
12
#38250000
1*
14
#38300000
1)
0*
04
13
#38350000
1*
14
#38400000
1"
0#
0$
0%
0&
0'
0(
0)
0*
04
03
02
01
00
0/
0.
0-
1,
#38450000
1*
14
#38500000
1)
0*
04
13
#38550000
1*
14
#38600000
1(
0)
0*
04
03
12
#38650000
1*
14
#38700000
1)
0*
04
13
#38750000
1*
14
#38800000
1'
0(
0)
0*
04
03
02
11
#38850000
1*
14
#38900000
1)
0*
04
13
#38950000
1*
14
#39000000
1(
0)
0*
04
03
12
#39050000
1*
14
#39100000
1)
0*
04
13
#39150000
1*
14
#39200000
1&
0'
0(
0)
0*
04
03
02
01
10
#39250000
1*
14
#39300000
1)
0*
04
13
#39350000
1*
14
#39400000
1(
0)
0*
04
03
12
#39450000
1*
14
#39500000
1)
0*
04
13
#39550000
1*
14
#39600000
1'
0(
0)
0*
04
03
02
11
#39650000
1*
14
#39700000
1)
0*
04
13
#39750000
1*
14
#39800000
1(
0)
0*
04
03
12
#39850000
1*
14
#39900000
1)
0*
04
13
#39950000
1*
14
#40000000
1%
0&
0'
0(
0)
0*
04
03
02
01
00
1/
#40050000
1*
14
#40100000
1)
0*
04
13
#40150000
1*
14
#40200000
1(
0)
0*
04
03
12
#40250000
1*
14
#40300000
1)
0*
04
13
#40350000
1*
14
#40400000
1'
0(
0)
0*
04
03
02
11
#40450000
1*
14
#40500000
1)
0*
04
13
#40550000
1*
14
#40600000
1(
0)
0*
04
03
12
#40650000
1*
14
#40700000
1)
0*
04
13
#40750000
1*
14
#40800000
1&
0'
0(
0)
0*
04
03
02
01
10
#40850000
1*
14
#40900000
1)
0*
04
13
#40950000
1*
14
#41000000
1(
0)
0*
04
03
12
#41050000
1*
14
#41100000
1)
0*
04
13
#41150000
1*
14
#41200000
1'
0(
0)
0*
04
03
02
11
#41250000
1*
14
#41300000
1)
0*
04
13
#41350000
1*
14
#41400000
1(
0)
0*
04
03
12
#41450000
1*
14
#41500000
1)
0*
04
13
#41550000
1*
14
#41600000
1$
0%
0&
0'
0(
0)
0*
04
03
02
01
00
0/
1.
#41650000
1*
14
#41700000
1)
0*
04
13
#41750000
1*
14
#41800000
1(
0)
0*
04
03
12
#41850000
1*
14
#41900000
1)
0*
04
13
#41950000
1*
14
#42000000
1'
0(
0)
0*
04
03
02
11
#42050000
1*
14
#42100000
1)
0*
04
13
#42150000
1*
14
#42200000
1(
0)
0*
04
03
12
#42250000
1*
14
#42300000
1)
0*
04
13
#42350000
1*
14
#42400000
1&
0'
0(
0)
0*
04
03
02
01
10
#42450000
1*
14
#42500000
1)
0*
04
13
#42550000
1*
14
#42600000
1(
0)
0*
04
03
12
#42650000
1*
14
#42700000
1)
0*
04
13
#42750000
1*
14
#42800000
1'
0(
0)
0*
04
03
02
11
#42850000
1*
14
#42900000
1)
0*
04
13
#42950000
1*
14
#43000000
1(
0)
0*
04
03
12
#43050000
1*
14
#43100000
1)
0*
04
13
#43150000
1*
14
#43200000
1%
0&
0'
0(
0)
0*
04
03
02
01
00
1/
#43250000
1*
14
#43300000
1)
0*
04
13
#43350000
1*
14
#43400000
1(
0)
0*
04
03
12
#43450000
1*
14
#43500000
1)
0*
04
13
#43550000
1*
14
#43600000
1'
0(
0)
0*
04
03
02
11
#43650000
1*
14
#43700000
1)
0*
04
13
#43750000
1*
14
#43800000
1(
0)
0*
04
03
12
#43850000
1*
14
#43900000
1)
0*
04
13
#43950000
1*
14
#44000000
1&
0'
0(
0)
0*
04
03
02
01
10
#44050000
1*
14
#44100000
1)
0*
04
13
#44150000
1*
14
#44200000
1(
0)
0*
04
03
12
#44250000
1*
14
#44300000
1)
0*
04
13
#44350000
1*
14
#44400000
1'
0(
0)
0*
04
03
02
11
#44450000
1*
14
#44500000
1)
0*
04
13
#44550000
1*
14
#44600000
1(
0)
0*
04
03
12
#44650000
1*
14
#44700000
1)
0*
04
13
#44750000
1*
14
#44800000
1#
0$
0%
0&
0'
0(
0)
0*
04
03
02
01
00
0/
0.
1-
#44850000
1*
14
#44900000
1)
0*
04
13
#44950000
1*
14
#45000000
1(
0)
0*
04
03
12
#45050000
1*
14
#45100000
1)
0*
04
13
#45150000
1*
14
#45200000
1'
0(
0)
0*
04
03
02
11
#45250000
1*
14
#45300000
1)
0*
04
13
#45350000
1*
14
#45400000
1(
0)
0*
04
03
12
#45450000
1*
14
#45500000
1)
0*
04
13
#45550000
1*
14
#45600000
1&
0'
0(
0)
0*
04
03
02
01
10
#45650000
1*
14
#45700000
1)
0*
04
13
#45750000
1*
14
#45800000
1(
0)
0*
04
03
12
#45850000
1*
14
#45900000
1)
0*
04
13
#45950000
1*
14
#46000000
1'
0(
0)
0*
04
03
02
11
#46050000
1*
14
#46100000
1)
0*
04
13
#46150000
1*
14
#46200000
1(
0)
0*
04
03
12
#46250000
1*
14
#46300000
1)
0*
04
13
#46350000
1*
14
#46400000
1%
0&
0'
0(
0)
0*
04
03
02
01
00
1/
#46450000
1*
14
#46500000
1)
0*
04
13
#46550000
1*
14
#46600000
1(
0)
0*
04
03
12
#46650000
1*
14
#46700000
1)
0*
04
13
#46750000
1*
14
#46800000
1'
0(
0)
0*
04
03
02
11
#46850000
1*
14
#46900000
1)
0*
04
13
#46950000
1*
14
#47000000
1(
0)
0*
04
03
12
#47050000
1*
14
#47100000
1)
0*
04
13
#47150000
1*
14
#47200000
1&
0'
0(
0)
0*
04
03
02
01
10
#47250000
1*
14
#47300000
1)
0*
04
13
#47350000
1*
14
#47400000
1(
0)
0*
04
03
12
#47450000
1*
14
#47500000
1)
0*
04
13
#47550000
1*
14
#47600000
1'
0(
0)
0*
04
03
02
11
