tarefa1/part5.vhd
library ieee;
use ieee.std_logic_1164.all;

-- Rotação de caracteres em quatro displays

-- Multiplexador 4 para 1 de dois bits, equivalente ao circuito da Parte 3.
entity mux4_2bit is
    port (
        S          : in  std_logic_vector(1 downto 0);
        U, V, W, X : in  std_logic_vector(1 downto 0);
        M          : out std_logic_vector(1 downto 0)
    );
end mux4_2bit;

architecture behavioral of mux4_2bit is
begin
    process (S, U, V, W, X)
    begin
        case S is
            when "00"   => M <= U;
            when "01"   => M <= V;
            when "10"   => M <= W;
            when "11"   => M <= X;
            when others => M <= (others => '0');
        end case;
    end process;
end behavioral;

library ieee;
use ieee.std_logic_1164.all;

-- Decodificador da Parte 4. Os segmentos da DE0 sao ativos em nivel 0.
entity char_7seg is
    port (
        C       : in  std_logic_vector(1 downto 0);
        DISPLAY : out std_logic_vector(0 to 6)
    );
end char_7seg;

architecture rtl of char_7seg is
    constant CHAR_D     : std_logic_vector(0 to 6) := "1000010";
    constant CHAR_E     : std_logic_vector(0 to 6) := "0110000";
    constant CHAR_0     : std_logic_vector(0 to 6) := "0000001";
    constant CHAR_BLANK : std_logic_vector(0 to 6) := "1111111";
begin
    with C select
        DISPLAY <= CHAR_D     when "00",
                   CHAR_E     when "01",
                   CHAR_0     when "10",
                   CHAR_BLANK when others;
end rtl;

library ieee;
use ieee.std_logic_1164.all;

entity part5 is
    port (
        SW                   : in  std_logic_vector(9 downto 0);
        LEDG                 : out std_logic_vector(9 downto 0);
        HEX3, HEX2, HEX1, HEX0 : out std_logic_vector(0 to 6)
    );
end part5;

-- arquitetura estrutural, conectando instancias

architecture structural of part5 is
    signal SELECTOR                   : std_logic_vector(1 downto 0);
    signal CH0, CH1, CH2, CH3         : std_logic_vector(1 downto 0);
    signal H3_CHAR, H2_CHAR, H1_CHAR, H0_CHAR : std_logic_vector(1 downto 0);
begin
    LEDG <= SW;

    SELECTOR <= SW(9 downto 8);
    CH0 <= SW(7 downto 6);
    CH1 <= SW(5 downto 4);
    CH2 <= SW(3 downto 2);
    CH3 <= SW(1 downto 0);

    MUX_HEX3 : entity work.mux4_2bit(behavioral)
        port map (SELECTOR, CH0, CH1, CH2, CH3, H3_CHAR);

    MUX_HEX2 : entity work.mux4_2bit(behavioral)
        port map (SELECTOR, CH1, CH2, CH3, CH0, H2_CHAR);

    MUX_HEX1 : entity work.mux4_2bit(behavioral)
        port map (SELECTOR, CH2, CH3, CH0, CH1, H1_CHAR);

    MUX_HEX0 : entity work.mux4_2bit(behavioral)
        port map (SELECTOR, CH3, CH0, CH1, CH2, H0_CHAR);

    DEC_HEX3 : entity work.char_7seg(rtl) port map (H3_CHAR, HEX3);
    DEC_HEX2 : entity work.char_7seg(rtl) port map (H2_CHAR, HEX2);
    DEC_HEX1 : entity work.char_7seg(rtl) port map (H1_CHAR, HEX1);
    DEC_HEX0 : entity work.char_7seg(rtl) port map (H0_CHAR, HEX0);
end structural;

tarefa1/part5_tb.vhd
library ieee;
use ieee.std_logic_1164.all;
use ieee.numeric_std.all;

entity part5_tb is
end part5_tb;

architecture test of part5_tb is
    signal SW                   : std_logic_vector(9 downto 0) := (others => '0');
    signal LEDG                 : std_logic_vector(9 downto 0);
    signal HEX3, HEX2, HEX1, HEX0 : std_logic_vector(0 to 6);

    type code_array is array (0 to 3) of std_logic_vector(1 downto 0);

    function decode(C : std_logic_vector(1 downto 0))
        return std_logic_vector is
    begin
        case C is
            when "00"   => return "1000010"; -- d
            when "01"   => return "0110000"; -- E
            when "10"   => return "0000001"; -- 0
            when others => return "1111111"; -- apagado
        end case;
    end function;
begin
    DUT : entity work.part5(structural)
        port map (SW, LEDG, HEX3, HEX2, HEX1, HEX0);

    stimulus : process
        variable sw_value : std_logic_vector(9 downto 0);
        variable chars    : code_array;
        variable rotation : integer;
    begin
        for value in 0 to 1023 loop
            sw_value := std_logic_vector(to_unsigned(value, SW'length));
            SW <= sw_value;
            wait for 1 ns;

            chars(0) := sw_value(7 downto 6);
            chars(1) := sw_value(5 downto 4);
            chars(2) := sw_value(3 downto 2);
            chars(3) := sw_value(1 downto 0);
            rotation := to_integer(unsigned(sw_value(9 downto 8)));

            assert LEDG = sw_value
                report "LEDG nao acompanha SW" severity failure;
            assert HEX3 = decode(chars((rotation + 0) mod 4))
                report "Rotacao incorreta em HEX3" severity failure;
            assert HEX2 = decode(chars((rotation + 1) mod 4))
                report "Rotacao incorreta em HEX2" severity failure;
            assert HEX1 = decode(chars((rotation + 2) mod 4))
                report "Rotacao incorreta em HEX1" severity failure;
            assert HEX0 = decode(chars((rotation + 3) mod 4))
                report "Rotacao incorreta em HEX0" severity failure;
        end loop;

        report "Parte 5: todas as 1024 combinacoes aprovadas" severity note;
        wait;
    end process;
end test;

tarefa1/part5.vcd
$date
	Mon Sep 14 19:02:58 2026
$end
$version
	ModelSim Version 10.1d
$end
$timescale
	1ps
$end
$scope module part5_tb $end
$var wire 1 ! SW [9] $end
$var wire 1 " SW [8] $end
$var wire 1 # SW [7] $end
$var wire 1 $ SW [6] $end
$var wire 1 % SW [5] $end
$var wire 1 & SW [4] $end
$var wire 1 ' SW [3] $end
$var wire 1 ( SW [2] $end
$var wire 1 ) SW [1] $end
$var wire 1 * SW [0] $end
$var wire 1 + LEDG [9] $end
$var wire 1 , LEDG [8] $end
$var wire 1 - LEDG [7] $end
$var wire 1 . LEDG [6] $end
$var wire 1 / LEDG [5] $end
$var wire 1 0 LEDG [4] $end
$var wire 1 1 LEDG [3] $end
$var wire 1 2 LEDG [2] $end
$var wire 1 3 LEDG [1] $end
$var wire 1 4 LEDG [0] $end
$var wire 1 5 HEX3 [0] $end
$var wire 1 6 HEX3 [1] $end
$var wire 1 7 HEX3 [2] $end
$var wire 1 8 HEX3 [3] $end
$var wire 1 9 HEX3 [4] $end
$var wire 1 : HEX3 [5] $end
$var wire 1 ; HEX3 [6] $end
$var wire 1 < HEX2 [0] $end
$var wire 1 = HEX2 [1] $end
$var wire 1 > HEX2 [2] $end
$var wire 1 ? HEX2 [3] $end
$var wire 1 @ HEX2 [4] $end
$var wire 1 A HEX2 [5] $end
$var wire 1 B HEX2 [6] $end
$var wire 1 C HEX1 [0] $end
$var wire 1 D HEX1 [1] $end
$var wire 1 E HEX1 [2] $end
$var wire 1 F HEX1 [3] $end
$var wire 1 G HEX1 [4] $end
$var wire 1 H HEX1 [5] $end
$var wire 1 I HEX1 [6] $end
$var wire 1 J HEX0 [0] $end
$var wire 1 K HEX0 [1] $end
$var wire 1 L HEX0 [2] $end
$var wire 1 M HEX0 [3] $end
$var wire 1 N HEX0 [4] $end
$var wire 1 O HEX0 [5] $end
$var wire 1 P HEX0 [6] $end
$scope module DUT $end
$var wire 1 ! SW [9] $end
$var wire 1 " SW [8] $end
$var wire 1 # SW [7] $end
$var wire 1 $ SW [6] $end
$var wire 1 % SW [5] $end
$var wire 1 & SW [4] $end
$var wire 1 ' SW [3] $end
$var wire 1 ( SW [2] $end
$var wire 1 ) SW [1] $end
$var wire 1 * SW [0] $end
$var wire 1 + LEDG [9] $end
$var wire 1 , LEDG [8] $end
$var wire 1 - LEDG [7] $end
$var wire 1 . LEDG [6] $end
$var wire 1 / LEDG [5] $end
$var wire 1 0 LEDG [4] $end
$var wire 1 1 LEDG [3] $end
$var wire 1 2 LEDG [2] $end
$var wire 1 3 LEDG [1] $end
$var wire 1 4 LEDG [0] $end
$var wire 1 5 HEX3 [0] $end
$var wire 1 6 HEX3 [1] $end
$var wire 1 7 HEX3 [2] $end
$var wire 1 8 HEX3 [3] $end
$var wire 1 9 HEX3 [4] $end
$var wire 1 : HEX3 [5] $end
$var wire 1 ; HEX3 [6] $end
$var wire 1 < HEX2 [0] $end
$var wire 1 = HEX2 [1] $end
$var wire 1 > HEX2 [2] $end
$var wire 1 ? HEX2 [3] $end
$var wire 1 @ HEX2 [4] $end
$var wire 1 A HEX2 [5] $end
$var wire 1 B HEX2 [6] $end
$var wire 1 C HEX1 [0] $end
$var wire 1 D HEX1 [1] $end
$var wire 1 E HEX1 [2] $end
$var wire 1 F HEX1 [3] $end
$var wire 1 G HEX1 [4] $end
$var wire 1 H HEX1 [5] $end
$var wire 1 I HEX1 [6] $end
$var wire 1 J HEX0 [0] $end
$var wire 1 K HEX0 [1] $end
$var wire 1 L HEX0 [2] $end
$var wire 1 M HEX0 [3] $end
$var wire 1 N HEX0 [4] $end
$var wire 1 O HEX0 [5] $end
$var wire 1 P HEX0 [6] $end
$var wire 1 Q SELECTOR [1] $end
$var wire 1 R SELECTOR [0] $end
$var wire 1 S CH0 [1] $end
$var wire 1 T CH0 [0] $end
$var wire 1 U CH1 [1] $end
$var wire 1 V CH1 [0] $end
$var wire 1 W CH2 [1] $end
$var wire 1 X CH2 [0] $end
$var wire 1 Y CH3 [1] $end
$var wire 1 Z CH3 [0] $end
$var wire 1 [ H3_CHAR [1] $end
$var wire 1 \ H3_CHAR [0] $end
$var wire 1 ] H2_CHAR [1] $end
$var wire 1 ^ H2_CHAR [0] $end
$var wire 1 _ H1_CHAR [1] $end
$var wire 1 ` H1_CHAR [0] $end
$var wire 1 a H0_CHAR [1] $end
$var wire 1 b H0_CHAR [0] $end
$scope module MUX_HEX3 $end
$var wire 1 Q S [1] $end
$var wire 1 R S [0] $end
$var wire 1 S U [1] $end
$var wire 1 T U [0] $end
$var wire 1 U V [1] $end
$var wire 1 V V [0] $end
$var wire 1 W W [1] $end
$var wire 1 X W [0] $end
$var wire 1 Y X [1] $end
$var wire 1 Z X [0] $end
$var wire 1 [ M [1] $end
$var wire 1 \ M [0] $end
$upscope $end
$scope module MUX_HEX2 $end
$var wire 1 Q S [1] $end
$var wire 1 R S [0] $end
$var wire 1 U U [1] $end
$var wire 1 V U [0] $end
$var wire 1 W V [1] $end
$var wire 1 X V [0] $end
$var wire 1 Y W [1] $end
$var wire 1 Z W [0] $end
$var wire 1 S X [1] $end
$var wire 1 T X [0] $end
$var wire 1 ] M [1] $end
$var wire 1 ^ M [0] $end
$upscope $end
$scope module MUX_HEX1 $end
$var wire 1 Q S [1] $end
$var wire 1 R S [0] $end
$var wire 1 W U [1] $end
$var wire 1 X U [0] $end
$var wire 1 Y V [1] $end
$var wire 1 Z V [0] $end
$var wire 1 S W [1] $end
$var wire 1 T W [0] $end
$var wire 1 U X [1] $end
$var wire 1 V X [0] $end
$var wire 1 _ M [1] $end
$var wire 1 ` M [0] $end
$upscope $end
$scope module MUX_HEX0 $end
$var wire 1 Q S [1] $end
$var wire 1 R S [0] $end
$var wire 1 Y U [1] $end
$var wire 1 Z U [0] $end
$var wire 1 S V [1] $end
$var wire 1 T V [0] $end
$var wire 1 U W [1] $end
$var wire 1 V W [0] $end
$var wire 1 W X [1] $end
$var wire 1 X X [0] $end
$var wire 1 a M [1] $end
$var wire 1 b M [0] $end
$upscope $end
$scope module DEC_HEX3 $end
$var wire 1 [ C [1] $end
$var wire 1 \ C [0] $end
$var wire 1 5 DISPLAY [0] $end
$var wire 1 6 DISPLAY [1] $end
$var wire 1 7 DISPLAY [2] $end
$var wire 1 8 DISPLAY [3] $end
$var wire 1 9 DISPLAY [4] $end
$var wire 1 : DISPLAY [5] $end
$var wire 1 ; DISPLAY [6] $end
$upscope $end
$scope module DEC_HEX2 $end
$var wire 1 ] C [1] $end
$var wire 1 ^ C [0] $end
$var wire 1 < DISPLAY [0] $end
$var wire 1 = DISPLAY [1] $end
$var wire 1 > DISPLAY [2] $end
$var wire 1 ? DISPLAY [3] $end
$var wire 1 @ DISPLAY [4] $end
$var wire 1 A DISPLAY [5] $end
$var wire 1 B DISPLAY [6] $end
$upscope $end
$scope module DEC_HEX1 $end
$var wire 1 _ C [1] $end
$var wire 1 ` C [0] $end
$var wire 1 C DISPLAY [0] $end
$var wire 1 D DISPLAY [1] $end
$var wire 1 E DISPLAY [2] $end
$var wire 1 F DISPLAY [3] $end
$var wire 1 G DISPLAY [4] $end
$var wire 1 H DISPLAY [5] $end
$var wire 1 I DISPLAY [6] $end
$upscope $end
$scope module DEC_HEX0 $end
$var wire 1 a C [1] $end
$var wire 1 b C [0] $end
$var wire 1 J DISPLAY [0] $end
$var wire 1 K DISPLAY [1] $end
$var wire 1 L DISPLAY [2] $end
$var wire 1 M DISPLAY [3] $end
$var wire 1 N DISPLAY [4] $end
$var wire 1 O DISPLAY [5] $end
$var wire 1 P DISPLAY [6] $end
$upscope $end
$upscope $end
$upscope $end
$enddefinitions $end
#0
$dumpvars
0!
0"
0#
0$
0%
0&
0'
0(
0)
0*
0+
0,
0-
0.
0/
00
01
02
03
04
15
06
07
08
09
1:
0;
1<
0=
0>
0?
0@
1A
0B
1C
0D
0E
0F
0G
1H
0I
1J
0K
0L
0M
0N
1O
0P
0Q
0R
0S
0T
0U
0V
0W
0X
0Y
0Z
0[
0\
0]
0^
0_
0`
0a
0b
$end
#1000
1*
14
1Z
1b
0O
1L
1K
0J
#2000
0*
1)
04
13
0Z
1Y
0b
1a
1P
0L
0K
#3000
1*
14
1Z
1b
1O
1N
1M
1L
1K
1J
#4000
0*
0)
1(
04
03
12
0Z
0Y
1X
1`
0b
0a
0H
1E
1D
0C
0P
0N
0M
0L
0K
#5000
1*
14
1Z
1b
0O
1L
1K
0J
#6000
0*
1)
04
13
0Z
1Y
0b
1a
1P
0L
0K
#7000
1*
14
1Z
1b
1O
1N
1M
1L
1K
1J
#8000
0*
0)
0(
1'
04
03
02
11
0Z
0Y
0X
1W
0`
1_
0b
0a
1I
0E
0D
0P
0N
0M
0L
0K
#9000
1*
14
1Z
1b
0O
1L
1K
0J
#10000
0*
1)
04
13
0Z
1Y
0b
1a
1P
0L
0K
#11000
1*
14
1Z
1b
1O
1N
1M
1L
1K
1J
#12000
0*
0)
1(
04
03
12
0Z
0Y
1X
1`
0b
0a
1H
1G
1F
1E
1D
1C
0P
0N
0M
0L
0K
#13000
1*
14
1Z
1b
0O
1L
1K
0J
#14000
0*
1)
04
13
0Z
1Y
0b
1a
1P
0L
0K
#15000
1*
14
1Z
1b
1O
1N
1M
1L
1K
1J
#16000
0*
0)
0(
0'
1&
04
03
02
01
10
0Z
0Y
0X
0W
1V
1^
0`
0_
0b
0a
0A
1>
1=
0<
0I
0G
0F
0E
0D
0P
0N
0M
0L
0K
#17000
1*
14
1Z
1b
0O
1L
1K
0J
#18000
0*
1)
04
13
0Z
1Y
0b
1a
1P
0L
0K
#19000
1*
14
1Z
1b
1O
1N
1M
1L
1K
1J
#20000
0*
0)
1(
04
03
12
0Z
0Y
1X
1`
0b
0a
0H
1E
1D
0C
0P
0N
0M
0L
0K
#21000
1*
14
1Z
1b
0O
1L
1K
0J
#22000
0*
1)
04
13
0Z
1Y
0b
1a
1P
0L
0K
#23000
1*
14
1Z
1b
1O
1N
1M
1L
1K
1J
#24000
0*
0)
0(
1'
04
03
02
11
0Z
0Y
0X
1W
0`
1_
0b
0a
1I
0E
0D
0P
0N
0M
0L
0K
#25000
1*
14
1Z
1b
0O
1L
1K
0J
#26000
0*
1)
04
13
0Z
1Y
0b
1a
1P
0L
0K
#27000
1*
14
1Z
1b
1O
1N
1M
1L
1K
1J
#28000
0*
0)
1(
04
03
12
0Z
0Y
1X
1`
0b
0a
1H
1G
1F
1E
1D
1C
0P
0N
0M
0L
0K
#29000
1*
14
1Z
1b
0O
1L
1K
0J
#30000
0*
1)
04
13
0Z
1Y
0b
1a
1P
0L
0K
#31000
1*
14
1Z
1b
1O
1N
1M
1L
1K
1J
#32000
0*
0)
0(
0'
0&
1%
04
03
02
01
00
1/
0Z
0Y
0X
0W
0V
1U
0^
1]
0`
0_
0b
0a
1B
0>
0=
0I
0G
0F
0E
0D
0P
0N
0M
0L
0K
#33000
1*
14
1Z
1b
0O
1L
1K
0J
#34000
0*
1)
04
13
0Z
1Y
0b
1a
1P
0L
0K
#35000
1*
14
1Z
1b
1O
1N
1M
1L
1K
1J
#36000
0*
0)
1(
04
03
12
0Z
0Y
1X
1`
0b
0a
0H
1E
1D
0C
0P
0N
0M
0L
0K
#37000
1*
14
1Z
1b
0O
1L
1K
0J
#38000
0*
1)
04
13
0Z
1Y
0b
1a
1P
0L
0K
#39000
1*
14
1Z
1b
1O
1N
1M
1L
1K
1J
#40000
0*
0)
0(
1'
04
03
02
11
0Z
0Y
0X
1W
0`
1_
0b
0a
1I
0E
0D
0P
0N
0M
0L
0K
#41000
1*
14
1Z
1b
0O
1L
1K
0J
#42000
0*
1)
04
13
0Z
1Y
0b
1a
1P
0L
0K
#43000
1*
14
1Z
1b
1O
1N
1M
1L
1K
1J
#44000
0*
0)
1(
04
03
12
0Z
0Y
1X
1`
0b
0a
1H
1G
1F
1E
1D
1C
0P
0N
0M
0L
0K
#45000
1*
14
1Z
1b
0O
1L
1K
0J
#46000
0*
1)
04
13
0Z
1Y
0b
1a
1P
0L
0K
#47000
1*
14
1Z
1b
1O
1N
1M
1L
1K
1J
#48000
0*
0)
0(
0'
1&
04
03
02
01
10
0Z
0Y
0X
0W
1V
1^
0`
0_
0b
0a
1A
1@
1?
1>
1=
1<
0I
0G
0F
0E
0D
0P
0N
0M
0L
0K
#49000
1*
14
1Z
1b
0O
1L
1K
0J
#50000
0*
1)
04
13
0Z
1Y
0b
1a
1P
0L
0K
#51000
1*
14
1Z
1b
1O
1N
1M
1L
1K
1J
#52000
0*
0)
1(
04
03
12
0Z
0Y
1X
1`
0b
0a
0H
1E
1D
0C
0P
0N
0M
0L
0K
#53000
1*
14
1Z
1b
0O
1L
1K
0J
#54000
0*
1)
04
13
0Z
1Y
0b
1a
1P
0L
0K
#55000
1*
14
1Z
1b
1O
1N
1M
1L
1K
1J
#56000
0*
0)
0(
1'
04
03
02
11
0Z
0Y
0X
1W
0`
1_
0b
0a
1I
0E
0D
0P
0N
0M
0L
0K
#57000
1*
14
1Z
1b
0O
1L
1K
0J
#58000
0*
1)
04
13
0Z
1Y
0b
1a
1P
0L
0K
#59000
1*
14
1Z
1b
1O
1N
1M
1L
1K
1J
#60000
0*
0)
1(
04
03
12
0Z
0Y
1X
1`
0b
0a
1H
1G
1F
1E
1D
1C
0P
0N
0M
0L
0K
#61000
1*
14
1Z
1b
0O
1L
1K
0J
#62000
0*
1)
04
13
0Z
1Y
0b
1a
1P
0L
0K
#63000
1*
14
1Z
1b
1O
1N
1M
1L
1K
1J
#64000
0*
0)
0(
0'
0&
0%
1$
04
03
02
01
00
0/
1.
0Z
0Y
0X
0W
0V
0U
1T
1\
0^
0]
0`
0_
0b
0a
0:
17
16
05
0B
0@
0?
0>
0=
0I
0G
0F
0E
0D
0P
0N
0M
0L
0K
#65000
1*
14
1Z
1b
0O
1L
1K
0J
#66000
0*
1)
04
13
0Z
1Y
0b
1a
1P
0L
0K
#67000
1*
14
1Z
1b
1O
1N
1M
1L
1K
1J
#68000
0*
0)
1(
04
03
12
0Z
0Y
1X
1`
0b
0a
0H
1E
1D
0C
0P
0N
0M
0L
0K
#69000
1*
14
1Z
1b
0O
1L
1K
0J
#70000
0*
1)
04
13
0Z
1Y
0b
1a
1P
0L
0K
#71000
1*
14
1Z
1b
1O
1N
1M
1L
1K
1J
#72000
0*
0)
0(
1'
04
03
02
11
0Z
0Y
0X
1W
0`
1_
0b
0a
1I
0E
0D
0P
0N
0M
0L
0K
#73000
1*
14
1Z
1b
0O
1L
1K
0J
#74000
0*
1)
04
13
0Z
1Y
0b
1a
1P
0L
0K
#75000
1*
14
1Z
1b
1O
1N
1M
1L
1K
1J
#76000
0*
0)
1(
04
03
12
0Z
0Y
1X
1`
0b
0a
1H
1G
1F
1E
1D
1C
0P
0N
0M
0L
0K
#77000
1*
14
1Z
1b
0O
1L
1K
0J
#78000
0*
1)
04
13
0Z
1Y
0b
1a
1P
0L
0K
#79000
1*
14
1Z
1b
1O
1N
1M
1L
1K
1J
#80000
0*
0)
0(
0'
1&
04
03
02
01
10
0Z
0Y
0X
0W
1V
1^
0`
0_
0b
0a
0A
1>
1=
0<
0I
0G
0F
0E
0D
0P
0N
0M
0L
0K
#81000
1*
14
1Z
1b
0O
1L
1K
0J
#82000
0*
1)
04
13
0Z
1Y
0b
1a
1P
0L
0K
#83000
1*
14
1Z
1b
1O
1N
1M
1L
1K
1J
#84000
0*
0)
1(
04
03
12
0Z
0Y
1X
1`
0b
0a
0H
1E
1D
0C
0P
0N
0M
0L
0K
#85000
1*
14
1Z
1b
0O
1L
1K
0J
#86000
0*
1)
04
13
0Z
1Y
0b
1a
1P
0L
0K
#87000
1*
14
1Z
1b
1O
1N
1M
1L
1K
1J
#88000
0*
0)
0(
1'
04
03
02
11
0Z
0Y
0X
1W
0`
1_
0b
0a
1I
0E
0D
0P
0N
0M
0L
0K
#89000
1*
14
1Z
1b
0O
1L
1K
0J
#90000
0*
1)
04
13
0Z
1Y
0b
1a
1P
0L
0K
#91000
1*
14
1Z
1b
1O
1N
1M
1L
1K
1J
#92000
0*
0)
1(
04
03
12
0Z
0Y
1X
1`
0b
0a
1H
1G
1F
1E
1D
1C
0P
0N
0M
0L
0K
#93000
1*
14
1Z
1b
0O
1L
1K
0J
#94000
0*
1)
04
13
0Z
1Y
0b
1a
1P
0L
0K
#95000
1*
14
1Z
1b
1O
1N
1M
1L
1K
1J
#96000
0*
0)
0(
0'
0&
1%
04
03
02
01
00
1/
0Z
0Y
0X
0W
0V
1U
0^
1]
0`
0_
0b
0a
1B
0>
0=
0I
0G
0F
0E
0D
0P
0N
0M
0L
0K
#97000
1*
14
1Z
1b
0O
1L
1K
0J
#98000
0*
1)
04
13
0Z
1Y
0b
1a
1P
0L
0K
#99000
1*
14
1Z
1b
1O
1N
1M
1L
1K
1J
#100000
0*
0)
1(
04
03
12
0Z
0Y
1X
1`
0b
0a
0H
1E
1D
0C
0P
0N
0M
0L
0K
#101000
1*
14
1Z
1b
0O
1L
1K
0J
#102000
0*
1)
04
13
0Z
1Y
0b
1a
1P
0L
0K
#103000
1*
14
1Z
1b
1O
1N
1M
1L
1K
1J
#104000
0*
0)
0(
1'
04
03
02
11
0Z
0Y
0X
1W
0`
1_
0b
0a
1I
0E
0D
0P
0N
0M
0L
0K
#105000
1*
14
1Z
1b
0O
1L
1K
0J
#106000
0*
1)
04
13
0Z
1Y
0b
1a
1P
0L
0K
#107000
1*
14
1Z
1b
1O
1N
1M
1L
1K
1J
#108000
0*
0)
1(
04
03
12
0Z
0Y
1X
1`
0b
0a
1H
1G
1F
1E
1D
1C
0P
0N
0M
0L
0K
#109000
1*
14
1Z
1b
0O
1L
1K
0J
#110000
0*
1)
04
13
0Z
1Y
0b
1a
1P
0L
0K
#111000
1*
14
1Z
1b
1O
1N
1M
1L
1K
1J
#112000
0*
0)
0(
0'
1&
04
03
02
01
10
0Z
0Y
0X
0W
1V
1^
0`
0_
0b
0a
1A
1@
1?
1>
1=
1<
0I
0G
0F
0E
0D
0P
0N
0M
0L
0K
#113000
1*
14
1Z
1b
0O
1L
1K
0J
#114000
0*
1)
04
13
0Z
1Y
0b
1a
1P
0L
0K
#115000
1*
14
1Z
1b
1O
1N
1M
1L
1K
1J
#116000
0*
0)
1(
04
03
12
0Z
0Y
1X
1`
0b
0a
0H
1E
1D
0C
0P
0N
0M
0L
0K
#117000
1*
14
1Z
1b
0O
1L
1K
0J
#118000
0*
1)
04
13
0Z
1Y
0b
1a
1P
0L
0K
#119000
1*
14
1Z
1b
1O
1N
1M
1L
1K
1J
#120000
0*
0)
0(
1'
04
03
02
11
0Z
0Y
0X
1W
0`
1_
0b
0a
1I
0E
0D
0P
0N
0M
0L
0K
#121000
1*
14
1Z
1b
0O
1L
1K
0J
#122000
0*
1)
04
13
0Z
1Y
0b
1a
1P
0L
0K
#123000
1*
14
1Z
1b
1O
1N
1M
1L
1K
1J
#124000
0*
0)
1(
04
03
12
0Z
0Y
1X
1`
0b
0a
1H
1G
1F
1E
1D
1C
0P
0N
0M
0L
0K
#125000
1*
14
1Z
1b
0O
1L
1K
0J
#126000
0*
1)
04
13
0Z
1Y
0b
1a
1P
0L
0K
#127000
1*
14
1Z
1b
1O
1N
1M
1L
1K
1J
#128000
0*
0)
0(
0'
0&
0%
0$
1#
04
03
02
01
00
0/
0.
1-
0Z
0Y
0X
0W
0V
0U
0T
1S
0\
1[
0^
0]
0`
0_
0b
0a
1;
07
06
0B
0@
0?
0>
0=
0I
0G
0F
0E
0D
0P
0N
0M
0L
0K
#129000
1*
14
1Z
1b
0O
1L
1K
0J
#130000
0*
1)
04
13
0Z
1Y
0b
1a
1P
0L
0K
#131000
1*
14
1Z
1b
1O
1N
1M
1L
1K
1J
#132000
0*
0)
1(
04
03
12
0Z
0Y
1X
1`
0b
0a
0H
1E
1D
0C
0P
0N
0M
0L
0K
#133000
1*
14
1Z
1b
0O
1L
1K
0J
#134000
0*
1)
04
13
0Z
1Y
0b
1a
1P
0L
0K
#135000
1*
14
1Z
1b
1O
1N
1M
1L
1K
1J
#136000
0*
0)
0(
1'
04
03
02
11
0Z
0Y
0X
1W
0`
1_
0b
0a
1I
0E
0D
0P
0N
0M
0L
0K
#137000
1*
14
1Z
1b
0O
1L
1K
0J
#138000
0*
1)
04
13
0Z
1Y
0b
1a
1P
0L
0K
#139000
1*
14
1Z
1b
1O
1N
1M
1L
1K
1J
#140000
0*
0)
1(
04
03
12
0Z
0Y
1X
1`
0b
0a
1H
1G
1F
1E
1D
1C
0P
0N
0M
0L
0K
#141000
1*
14
1Z
1b
0O
1L
1K
0J
#142000
0*
1)
04
13
0Z
1Y
0b
1a
1P
0L
0K
#143000
1*
14
1Z
1b
1O
1N
1M
1L
1K
1J
#144000
0*
0)
0(
0'
1&
04
03
02
01
10
0Z
0Y
0X
0W
1V
1^
0`
0_
0b
0a
0A
1>
1=
0<
0I
0G
0F
0E
0D
0P
0N
0M
0L
0K
#145000
1*
14
1Z
1b
0O
1L
1K
0J
#146000
0*
1)
04
13
0Z
1Y
0b
1a
1P
0L
0K
#147000
1*
14
1Z
1b
1O
1N
1M
1L
1K
1J
#148000
0*
0)
1(
04
03
12
0Z
0Y
1X
1`
0b
0a
0H
1E
1D
0C
0P
0N
0M
0L
0K
#149000
1*
14
1Z
1b
0O
1L
1K
0J
#150000
0*
1)
04
13
0Z
1Y
0b
1a
1P
0L
0K
#151000
1*
14
1Z
1b
1O
1N
1M
1L
1K
1J
#152000
0*
0)
0(
1'
04
03
02
11
0Z
0Y
0X
1W
0`
1_
0b
0a
1I
0E
0D
0P
0N
0M
0L
0K
#153000
1*
14
1Z
1b
0O
1L
1K
0J
#154000
0*
1)
04
13
0Z
1Y
0b
1a
1P
0L
0K
#155000
1*
14
1Z
1b
1O
1N
1M
1L
1K
1J
#156000
0*
0)
1(
04
03
12
0Z
0Y
1X
1`
0b
0a
1H
1G
1F
1E
1D
1C
0P
0N
0M
0L
0K
#157000
1*
14
1Z
1b
0O
1L
1K
0J
#158000
0*
1)
04
13
0Z
1Y
0b
1a
1P
0L
0K
#159000
1*
14
1Z
1b
1O
1N
1M
1L
1K
1J
#160000
0*
0)
0(
0'
0&
1%
04
03
02
01
00
1/
0Z
0Y
0X
0W
0V
1U
0^
1]
0`
0_
0b
0a
1B
0>
0=
0I
0G
0F
0E
0D
0P
0N
0M
0L
0K
#161000
1*
14
1Z
1b
0O
1L
1K
0J
#162000
0*
1)
04
13
0Z
1Y
0b
1a
1P
0L
0K
#163000
1*
14
1Z
1b
1O
1N
1M
1L
1K
1J
#164000
0*
0)
1(
04
03
12
0Z
0Y
1X
1`
0b
0a
0H
1E
1D
0C
0P
0N
0M
0L
0K
#165000
1*
14
1Z
1b
0O
1L
1K
0J
#166000
0*
1)
04
13
0Z
1Y
0b
1a
1P
0L
0K
#167000
1*
14
1Z
1b
1O
1N
1M
1L
1K
1J
#168000
0*
0)
0(
1'
04
03
02
11
0Z
0Y
0X
1W
0`
1_
0b
0a
1I
0E
0D
0P
0N
0M
0L
0K
#169000
1*
14
1Z
1b
0O
1L
1K
0J
#170000
0*
1)
04
13
0Z
1Y
0b
1a
1P
0L
0K
#171000
1*
14
1Z
1b
1O
1N
1M
1L
1K
1J
#172000
0*
0)
1(
04
03
12
0Z
0Y
1X
1`
0b
0a
1H
1G
1F
1E
1D
1C
0P
0N
0M
0L
0K
#173000
1*
14
1Z
1b
0O
1L
1K
0J
#174000
0*
1)
04
13
0Z
1Y
0b
1a
1P
0L
0K
#175000
1*
14
1Z
1b
1O
1N
1M
1L
1K
1J
#176000
0*
0)
0(
0'
1&
04
03
02
01
10
0Z
0Y
0X
0W
1V
1^
0`
0_
0b
0a
1A
1@
1?
1>
1=
1<
0I
0G
0F
0E
0D
0P
0N
0M
0L
0K
#177000
1*
14
1Z
1b
0O
1L
1K
0J
#178000
0*
1)
04
13
0Z
1Y
0b
1a
1P
0L
0K
#179000
1*
14
1Z
1b
1O
1N
1M
1L
1K
1J
#180000
0*
0)
1(
04
03
12
0Z
0Y
1X
1`
0b
0a
0H
1E
1D
0C
0P
0N
0M
0L
0K
#181000
1*
14
1Z
1b
0O
1L
1K
0J
#182000
0*
1)
04
13
0Z
1Y
0b
1a
1P
0L
0K
#183000
1*
14
1Z
1b
1O
1N
1M
1L
1K
1J
#184000
0*
0)
0(
1'
04
03
02
11
0Z
0Y
0X
1W
0`
1_
0b
0a
1I
0E
0D
0P
0N
0M
0L
0K
#185000
1*
14
1Z
1b
0O
1L
1K
0J
#186000
0*
1)
04
13
0Z
1Y
0b
1a
1P
0L
0K
#187000
1*
14
1Z
1b
1O
1N
1M
1L
1K
1J
#188000
0*
0)
1(
04
03
12
0Z
0Y
1X
1`
0b
0a
1H
1G
1F
1E
1D
1C
0P
0N
0M
0L
0K
#189000
1*
14
1Z
1b
0O
1L
1K
0J
#190000
0*
1)
04
13
0Z
1Y
0b
1a
1P
0L
0K
